{
  "hero": [
    {
      "id": "Thode Dur Thode Paas (2025) Season 1",
      "title": "Thode Dur Thode Paas (2025) Season 1",
      "poster": "https://m.media-amazon.com/images/M/MV5BYjhhODhkYjMtNzY2ZS00ZWY1LWJiNDctODA4MmE0YWEzOTRjXkEyXkFqcGc@._V1_FMjpg_UY853_.jpg",
      "stream_url": "https://jnaove.ydc1wes.me/hls2/02/00008/1xw8692ytkfp_,l,h,.urlset/master.m3u8?t=uc8cHbKclU8R88p3-8eYSjiPXMneOXAk0r2LkN1luLQ&s=1772484304&e=21600&f=42118&i=0.0&sp=0",
      "headers": {
        "Referer": "https://speedostream1.com/"
      }
    }
  ],
  "categories": [
    {
      "name": "Latest from input.json",
      "items": [
        {
          "id": "Thode Dur Thode Paas (2025) Season 1",
          "title": "Thode Dur Thode Paas (2025) Season 1",
          "poster": "https://m.media-amazon.com/images/M/MV5BYjhhODhkYjMtNzY2ZS00ZWY1LWJiNDctODA4MmE0YWEzOTRjXkEyXkFqcGc@._V1_FMjpg_UY853_.jpg",
          "stream_url": "https://jnaove.ydc1wes.me/hls2/02/00008/1xw8692ytkfp_,l,h,.urlset/master.m3u8?t=uc8cHbKclU8R88p3-8eYSjiPXMneOXAk0r2LkN1luLQ&s=1772484304&e=21600&f=42118&i=0.0&sp=0",
          "headers": {
            "Referer": "https://speedostream1.com/"
          }
        },
        {
          "id": "Operation Parindey (2020)",
          "title": "Operation Parindey (2020)",
          "poster": "https://m.media-amazon.com/images/M/MV5BMGFhOTc2NDctOTcwMi00YTRlLWFhMzgtZDZlNGNiODc2MmM3XkEyXkFqcGdeQXVyODE5NzE3OTE@._V1_UY853_.jpg",
          "stream_url": "https://jagur.ydc1wes.me/hls2/01/00007/t0zofvg2j7di_,l,h,.urlset/master.m3u8?t=IAvg0ELymQGSk70dhivHCHBvM1GM29aJSvFysRd7OBE&s=1772484305&e=21600&f=35005&i=0.0&sp=0",
          "headers": {
            "Referer": "https://speedostream1.com/"
          }
        },
        {
          "id": "Atkan Chatkan (2020)",
          "title": "Atkan Chatkan (2020)",
          "poster": "https://m.media-amazon.com/images/M/MV5BNmQzZTg4NWEtODgwYS00YTg2LWE4YzUtY2IwMWViN2U1NDkxXkEyXkFqcGc@._V1_FMjpg_UY480_.jpg",
          "stream_url": "https://tvhow.ydc1wes.me/hls2/02/00007/izwfoto0t7th_,l,h,.urlset/master.m3u8?t=fj0GHlVIF5cdd4CUUEq-8ZdplwUJlEhXppC7aWN5Vbk&s=1772484306&e=21600&f=38097&i=0.0&sp=0",
          "headers": {
            "Referer": "https://speedostream1.com/"
          }
        },
        {
          "id": "Janaawar – The Beast within (2025) Season 1",
          "title": "Janaawar – The Beast within (2025) Season 1",
          "poster": "https://m.media-amazon.com/images/M/MV5BY2M3YTVhYjEtNWNlMC00N2I5LWIyOGQtZTA0YzZmNjIyYjBjXkEyXkFqcGc@._V1_FMjpg_UX450_.jpg",
          "stream_url": "https://aamir.ydc1wes.me/hls2/01/00008/xb38ujoob7n5_,l,h,.urlset/master.m3u8?t=xrprInWQ6VEIIr_AQhLJ1F4kEcgUvjDeybqt-FJJzmA&s=1772484306&e=21600&f=41212&i=0.0&sp=0",
          "headers": {
            "Referer": "https://speedostream1.com/"
          }
        },
        {
          "id": "Bamfaad (2020)",
          "title": "Bamfaad (2020)",
          "poster": "https://m.media-amazon.com/images/M/MV5BNjNmYTI2NTUtZmYwNi00ZDBjLTgxOGItYzZmMmZmMWYyY2E3XkEyXkFqcGc@._V1_FMjpg_UY679_.jpg",
          "stream_url": "https://jnaove.ydc1wes.me/hls2/02/00008/6wjfq3qf1u4j_,l,h,.urlset/master.m3u8?t=fqczljPFBmM-vsN8ceGnzuueCXk2TpIQoJjLRCGuWAU&s=1772484307&e=21600&f=40864&i=0.0&sp=0",
          "headers": {
            "Referer": "https://speedostream1.com/"
          }
        },
        {
          "id": "The Wife (2021)",
          "title": "The Wife (2021)",
          "poster": "https://m.media-amazon.com/images/M/MV5BMjlmNmFhOGQtYjUyOC00Y2Q2LWFmOWQtYWJhMzc3NzRiZjAwXkEyXkFqcGdeQXVyMTI1NDAzMzM0._V1_FMjpg_UX640_.jpg",
          "stream_url": "https://jnaove.ydc1wes.me/hls2/02/00008/6i97uc9acnp4_,l,h,.urlset/master.m3u8?t=pzKCPxwSeY1KXn6Yo_cdsf6JdXQkbue3jgTgab76Zj0&s=1772484308&e=21600&f=40186&i=0.0&sp=0",
          "headers": {
            "Referer": "https://speedostream1.com/"
          }
        },
        {
          "id": "Bakaiti (2025) Season 1 (Zee5)",
          "title": "Bakaiti (2025) Season 1 (Zee5)",
          "poster": "https://m.media-amazon.com/images/M/MV5BNjE2NGE1NTQtNDE3My00OGRkLWEzMTQtMjllZWMxZTg5N2U0XkEyXkFqcGc@._V1_FMjpg_UY600_.jpg",
          "stream_url": "https://aamir.ydc1wes.me/hls2/01/00007/bgyuyaza461m_,l,h,.urlset/master.m3u8?t=igw3F49MKLpNbRXz9WtdIe-O_txgfftpQufnDEB5S68&s=1772484309&e=21600&f=39890&i=0.0&sp=0",
          "headers": {
            "Referer": "https://speedostream1.com/"
          }
        },
        {
          "id": "Chhal Kapat – The Deception (2025) Season 1 (Zee5)",
          "title": "Chhal Kapat – The Deception (2025) Season 1 (Zee5)",
          "poster": "https://m.media-amazon.com/images/M/MV5BM2M4MGRmZTctOTJjZi00OTE2LWEyZGQtNzc4OTM0NWViYzExXkEyXkFqcGc@._V1_FMjpg_UY853_.jpg",
          "stream_url": "https://aamir.ydc1wes.me/hls2/01/00007/kpuixdpcpa1j_,l,h,.urlset/master.m3u8?t=M7_Wtjg-vzp9ZR23l9peI8w3iVBwlNEWfgN4vF2HbZA&s=1772484309&e=21600&f=38720&i=0.0&sp=0",
          "headers": {
            "Referer": "https://speedostream1.com/"
          }
        },
        {
          "id": "Ayyana Mane (2025) Season 1 (Zee5)",
          "title": "Ayyana Mane (2025) Season 1 (Zee5)",
          "poster": "https://m.media-amazon.com/images/M/MV5BZTcxNzhkMzItNGZjMy00ZDlhLWI5NmYtNjIxYTFlMjRmOWMwXkEyXkFqcGc@._V1_FMjpg_UY853_.jpg",
          "stream_url": "https://aamir.ydc1wes.me/hls2/01/00007/wzc50p62c5i1_,l,h,.urlset/master.m3u8?t=EsCVmKG-VE_yzWprOcRuQyNFRn2Sij1ipOxLgTbYf50&s=1772484310&e=21600&f=38380&i=0.0&sp=0",
          "headers": {
            "Referer": "https://speedostream1.com/"
          }
        },
        {
          "id": "Shukranu (2020)",
          "title": "Shukranu (2020)",
          "poster": "https://m.media-amazon.com/images/M/MV5BNjQ0YjgzOTItN2RlYi00NzQ5LTg5MjUtNGE3MzI3MTU3MDY3XkEyXkFqcGdeQXVyMTA4NTc3NTQx._V1_FMjpg_UY580_.jpg",
          "stream_url": "https://arabic.ydc1wes.me/hls2/01/00007/8rnzng6x4rpr_,l,h,.urlset/master.m3u8?t=uMDY4zps5_fjP5sZsx-NYj5ah6VQzQTEreem2A-tQHY&s=1772484311&e=21600&f=36906&i=0.0&sp=0",
          "headers": {
            "Referer": "https://speedostream1.com/"
          }
        },
        {
          "id": "Silence: Can You Hear It (2021)",
          "title": "Silence: Can You Hear It (2021)",
          "poster": "https://m.media-amazon.com/images/M/MV5BYWI0YTBhZDctYzk5YS00ZGI5LTlhMmEtOWE1ODU5MjU1MGE1XkEyXkFqcGdeQXVyMTI1NDAzMzM0._V1_FMjpg_UX544_.jpg",
          "stream_url": "https://aamir.ydc1wes.me/hls2/01/00006/owoizuux1zpz_,l,h,.urlset/master.m3u8?t=VdowJHTvy1kCYN6IRyVieKWgKD22HrpOA_5dJvkZjMk&s=1772484311&e=21600&f=30894&i=0.0&sp=0",
          "headers": {
            "Referer": "https://speedostream1.com/"
          }
        },
        {
          "id": "Kaafir (2025)",
          "title": "Kaafir (2025)",
          "poster": "https://akamaividz2.zee5.com/image/upload/w_336,h_504,c_scale,f_webp,q_auto:eco/resources/0-0-1z5665928/portrait/1920x7700a8fde1937c74b8e89f143483d1c48e1473f2709aad847879bc32f194847456b.jpg",
          "stream_url": "https://aamir.ydc1wes.me/hls2/01/00007/1k5unl7du9bv_,l,h,.urlset/master.m3u8?t=YH6tQwGst-m19JylerKFiyo0n_2d8pEhNWO4pviOdYY&s=1772484312&e=21600&f=37583&i=0.0&sp=0",
          "headers": {
            "Referer": "https://speedostream1.com/"
          }
        },
        {
          "id": "Badnaam Gali (2019)",
          "title": "Badnaam Gali (2019)",
          "poster": "https://m.media-amazon.com/images/M/MV5BOGNlZjFhOTQtNDZhNS00NjlkLTkzYTYtMTE5YTc3NTQ0NzQxXkEyXkFqcGdeQXVyODE5NzE3OTE@._V1_FMjpg_UY694_.jpg",
          "stream_url": "https://jnaove.ydc1wes.me/hls2/02/00006/cgh2u2awkctn_,l,h,.urlset/master.m3u8?t=Slw4A-r-jpnpsOpPISWOK36VXFk-4bGhSfsdU7YLvH0&s=1772484313&e=21600&f=34137&i=0.0&sp=0",
          "headers": {
            "Referer": "https://speedostream1.com/"
          }
        },
        {
          "id": "Pyaar Testing (2025) Season 1 (Zee5)",
          "title": "Pyaar Testing (2025) Season 1 (Zee5)",
          "poster": "https://m.media-amazon.com/images/M/MV5BMTI3ZjFmNmEtNzc1NS00YTJhLWJjZDUtZTE2MTBkYTZiMTAxXkEyXkFqcGc@._V1_FMjpg_UY600_.jpg",
          "stream_url": "https://jnaove.ydc1wes.me/hls2/02/00007/85h1hzuy7ysm_,l,h,.urlset/master.m3u8?t=6BiWitNNRYJDtaRd-s4a6lAYYlrh055AXAHZA2QcZH0&s=1772484314&e=21600&f=36771&i=0.0&sp=0",
          "headers": {
            "Referer": "https://speedostream1.com/"
          }
        },
        {
          "id": "Crime Beat (2025) Season 1 (Zee5)",
          "title": "Crime Beat (2025) Season 1 (Zee5)",
          "poster": "https://m.media-amazon.com/images/M/MV5BOGZhOTgyNGQtY2IyMi00MjI1LWE3YTAtNjE5ZjIxYTI2YzIxXkEyXkFqcGc@._V1_FMjpg_UY853_.jpg",
          "stream_url": "https://aamir.ydc1wes.me/hls2/01/00007/,m9i88c5jxxmf_l,m9i88c5jxxmf_h,lang/eng/m9i88c5jxxmf_eng,.urlset/master.m3u8?t=9RAiB3VhCbWAOtddeJ3OK_BqeIGvkHyENAhtH0pUtro&s=1772484314&e=21600&f=36853&i=0.0&sp=0",
          "headers": {
            "Referer": "https://speedostream1.com/"
          }
        },
        {
          "id": "Griha Laxmi (2025) Season 1 (Zee5)",
          "title": "Griha Laxmi (2025) Season 1 (Zee5)",
          "poster": "https://m.media-amazon.com/images/M/MV5BNTc3ZjI2Y2ItYzM3OC00MGVlLTllZDgtN2RhMTcwMzA4MDcxXkEyXkFqcGc@._V1_FMjpg_UY693_.jpg",
          "stream_url": "https://aamir.ydc1wes.me/hls2/01/00007/mzrlc1p1ruqg_,l,h,.urlset/master.m3u8?t=jyMshD28MF6OH0Ef0zhV_roZiROE_APjuf2JcYDujmU&s=1772484315&e=21600&f=36229&i=0.0&sp=0",
          "headers": {
            "Referer": "https://speedostream1.com/"
          }
        },
        {
          "id": "Aindham Vedham (2024) Season 1 (Zee5)",
          "title": "Aindham Vedham (2024) Season 1 (Zee5)",
          "poster": "https://m.media-amazon.com/images/M/MV5BNThlZjE1ZWEtZTY4Yy00MzQwLWI3NjctYjFlODk3ZGFmNzk3XkEyXkFqcGc@._V1_FMjpg_UY600_.jpg",
          "stream_url": "https://aamir.ydc1wes.me/hls2/01/00007/oy0gmpa1n6y6_,l,h,.urlset/master.m3u8?t=eFqJ1UohkPvtw1cA7pEtFWET0A2kp2IfPczYSZiDAKY&s=1772484316&e=21600&f=35771&i=0.0&sp=0",
          "headers": {
            "Referer": "https://speedostream1.com/"
          }
        },
        {
          "id": "Khoj: Parchaiyo Ke Uss Paar (2024) Season 1 (Zee5)",
          "title": "Khoj: Parchaiyo Ke Uss Paar (2024) Season 1 (Zee5)",
          "poster": "https://m.media-amazon.com/images/M/MV5BYTNhOWI4NTYtNjQ1NC00OGEyLTgwYzAtNjM5YjJkMTIwYjA0XkEyXkFqcGc@._V1_FMjpg_UY853_.jpg",
          "stream_url": "https://aamir.ydc1wes.me/hls2/01/00007/85064uncke95_,l,h,.urlset/master.m3u8?t=9kaxlsX0xuuQQFf9M9g0KmxoMVtfwiEnzGqnryxjX7E&s=1772484317&e=21600&f=35958&i=0.0&sp=0",
          "headers": {
            "Referer": "https://speedostream1.com/"
          }
        },
        {
          "id": "Maeri (2024) Season 1 (Zee5)",
          "title": "Maeri (2024) Season 1 (Zee5)",
          "poster": "https://m.media-amazon.com/images/M/MV5BYzM1NTY2OTItM2FhZi00Njk3LWIyYWUtMDc2YjUwZWU3MjQ2XkEyXkFqcGc@._V1_FMjpg_UY640_.jpg",
          "stream_url": "https://jnaove.ydc1wes.me/hls2/02/00007/omfqoj9zo78u_,l,h,.urlset/master.m3u8?t=hrccIL9Tb8lXvQymQUHZQVPEnnGHBS38tMJyUBRY4rU&s=1772484317&e=21600&f=35660&i=0.0&sp=0",
          "headers": {
            "Referer": "https://speedostream1.com/"
          }
        },
        {
          "id": "Mithya (2024) Season 2 (Zee5 Original)",
          "title": "Mithya (2024) Season 2 (Zee5 Original)",
          "poster": "https://m.media-amazon.com/images/M/MV5BZDNkNTQ4NGYtYzc2ZC00YjRjLTliZGUtOTQ2MmY0NzNhNmIyXkEyXkFqcGc@._V1_FMjpg_UY600_.jpg",
          "stream_url": "https://aamir.ydc1wes.me/hls2/01/00007/552ulntgap80_,l,h,.urlset/master.m3u8?t=hXWc7gswFouXq3tEnTXG3Gp2Jhnbt35-BMXyfxTYvc0&s=1772484319&e=21600&f=35104&i=0.0&sp=0",
          "headers": {
            "Referer": "https://speedostream1.com/"
          }
        },
        {
          "id": "The Broken News (2024) Season 2 (Zee5)",
          "title": "The Broken News (2024) Season 2 (Zee5)",
          "poster": "https://m.media-amazon.com/images/M/MV5BY2Y3YmJhNDgtMzJhMS00M2JiLWE3NGQtYjVlODNkZTkxMjVkXkEyXkFqcGdeQXVyMTIyNzY0NTMx._V1_FMjpg_UY599_.jpg",
          "stream_url": "https://aamir.ydc1wes.me/hls2/01/00006/srdc3u9a24w8_,l,h,.urlset/master.m3u8?t=N9g2gk2kXNFTMmTjzXeTLZuFwiCwksP6g1fseqaJqXQ&s=1772484321&e=21600&f=31645&i=0.0&sp=0",
          "headers": {
            "Referer": "https://speedostream1.com/"
          }
        },
        {
          "id": "200: Halla Ho (2021)",
          "title": "200: Halla Ho (2021)",
          "poster": "https://m.media-amazon.com/images/M/MV5BYzczYWU5NzgtZDkxYi00NWZhLWFkZmQtNzdkZDZmNDgxNGEzXkEyXkFqcGdeQXVyMTIzMzg0MTM2._V1_FMjpg_UY720_.jpg",
          "stream_url": "https://dawn.ydc1wes.me/hls2/02/00006/71hqkva7l5wb_,l,h,.urlset/master.m3u8?t=nbDPkaegjVRYgTsEoC1EW4hffGYuVYJA9VvEXxyqz8s&s=1772484322&e=21600&f=31148&i=0.0&sp=0",
          "headers": {
            "Referer": "https://speedostream1.com/"
          }
        },
        {
          "id": "Sunflower (2024) Seeason 2 (Zee5 Original)",
          "title": "Sunflower (2024) Seeason 2 (Zee5 Original)",
          "poster": "https://m.media-amazon.com/images/M/MV5BYmY3NjQ4ODQtNzkzNS00NmVkLTg4NGYtMjA3ZmFhYjgyNmY5XkEyXkFqcGdeQXVyMTIzMzg0MTM2._V1_FMjpg_UY600_.jpg",
          "stream_url": "https://aamir.ydc1wes.me/hls2/01/00006/zijqawpsnn3g_,l,h,.urlset/master.m3u8?t=mhzno0zR9ojjkSw84Mddv5GqxA7ITp-ZnBoO9K4c54U&s=1772484322&e=21600&f=30201&i=0.0&sp=0",
          "headers": {
            "Referer": "https://speedostream1.com/"
          }
        },
        {
          "id": "Zehan (2024)",
          "title": "Zehan (2024)",
          "poster": "https://www.themoviedb.org/t/p/w600_and_h900_bestv2/8qZW4n704CjO2QWnM3uxPQ2ghW6.jpg",
          "stream_url": "https://jesse.ydc1wes.me/hls2/02/00005/d61iaovgafqe_,l,h,.urlset/master.m3u8?t=CN_P4gnuKHr4tVwK1gXRh1F5UR0KizFu20qcsm_3dzw&s=1772484323&e=21600&f=29645&i=0.0&sp=0",
          "headers": {
            "Referer": "https://speedostream1.com/"
          }
        },
        {
          "id": "Tatlubaaz (2023) Season 1 (Zee5)",
          "title": "Tatlubaaz (2023) Season 1 (Zee5)",
          "poster": "https://m.media-amazon.com/images/M/MV5BODM4OTRhMzYtMDM4ZS00MDI5LWE5MWUtZGZjYjY3NDQzZGY0XkEyXkFqcGdeQXVyMTcyNDI3MTQz._V1_FMjpg_UY576_.jpg",
          "stream_url": "https://rasoutin.ydc1wes.me/hls2/01/00005/qrxmj54fgups_,l,h,.urlset/master.m3u8?t=eY9O-wyNMHm17hil648689yvFqobxmqlYdRATIIcp04&s=1772484324&e=21600&f=28855&i=0.0&sp=0",
          "headers": {
            "Referer": "https://speedostream1.com/"
          }
        },
        {
          "id": "Pavitra Rishta Its Never Too Late (2021) Season 1 (Zee5 Original)",
          "title": "Pavitra Rishta Its Never Too Late (2021) Season 1 (Zee5 Original)",
          "poster": "https://m.media-amazon.com/images/M/MV5BNThiMTM4YmMtOWE5NS00YjNmLTg0YmItOTY2NDg5YmExMjg5XkEyXkFqcGdeQXVyMTIzMzg0MTM2._V1_FMjpg_UY720_.jpg",
          "stream_url": "https://rasoutin.ydc1wes.me/hls2/01/00007/bam221sjo2i3_,l,h,.urlset/master.m3u8?t=-455TLo5A_KmXg732eGGRqaoB_OeurGDNLTbGsVfy50&s=1772484325&e=21600&f=35281&i=0.0&sp=0",
          "headers": {
            "Referer": "https://speedostream1.com/"
          }
        },
        {
          "id": "Duranga (2023) Season 2 (Zee5)",
          "title": "Duranga (2023) Season 2 (Zee5)",
          "poster": "https://m.media-amazon.com/images/M/MV5BYjg2ZWUxNmQtNTdmZi00ODc0LTk5MjMtYWY4ZWM0M2JlNjg1XkEyXkFqcGdeQXVyMTIyNzY0NTMx._V1_FMjpg_UY576_.jpg",
          "stream_url": "https://aamir.ydc1wes.me/hls2/01/00005/yih48t4pbm27_,l,h,.urlset/master.m3u8?t=_h7zQKGkwYiGHeGuXKNhirjBggLxCOyE_w9afmyQR5Q&s=1772484325&e=21600&f=27772&i=0.0&sp=0",
          "headers": {
            "Referer": "https://speedostream1.com/"
          }
        },
        {
          "id": "Abar Proloy (2023) Season 1 Hindi Dubbed (Zee5 Original)",
          "title": "Abar Proloy (2023) Season 1 Hindi Dubbed (Zee5 Original)",
          "poster": "https://m.media-amazon.com/images/M/MV5BNjEwYjI5YjQtY2I3Yi00MDA3LWIwMjEtMDk1YzkxNTljMWYyXkEyXkFqcGdeQXVyMTIyNzY0NTMx._V1_FMjpg_UY720_.jpg",
          "stream_url": "https://aamir.ydc1wes.me/hls2/01/00005/x6ozhugcy59d_,l,h,.urlset/master.m3u8?t=3mVRoxBun27VoE4F5epC_-4sEoCoQ86RcUmQWk9NVvQ&s=1772484326&e=21600&f=27097&i=0.0&sp=0",
          "headers": {
            "Referer": "https://speedostream1.com/"
          }
        },
        {
          "id": "The Kashmir Files Unreported (2023) Season 1 (Zee5)",
          "title": "The Kashmir Files Unreported (2023) Season 1 (Zee5)",
          "poster": "https://ingfree.xyz/ib/UMV7r20ZHC.jpg",
          "stream_url": "https://jnaove.ydc1wes.me/hls2/02/00005/w5lg0otrgc8f_,l,h,.urlset/master.m3u8?t=d9ZJ8jhrnTGB9LsFzdBHK5ySpwELvUMx3riW7Keeo1U&s=1772484327&e=21600&f=26528&i=0.0&sp=0",
          "headers": {
            "Referer": "https://speedostream1.com/"
          }
        },
        {
          "id": "Baarish Aur Chowmein (2018)",
          "title": "Baarish Aur Chowmein (2018)",
          "poster": "https://m.media-amazon.com/images/M/MV5BMjk1ZTY3YTgtYzBmNy00ZmNmLWI3ZmQtNWQ4ZTUyMmU3NGJjXkEyXkFqcGdeQXVyNjE1OTQ0NjA@._V1_.jpg",
          "stream_url": "https://jnaove.ydc1wes.me/hls2/02/00005/zvll5guocuu0_,l,h,.urlset/master.m3u8?t=QfpSw8yw8qJXhRmG2NyN9xwngyRLqPA9mXGmUSwCd2g&s=1772484328&e=21600&f=26074&i=0.0&sp=0",
          "headers": {
            "Referer": "https://speedostream1.com/"
          }
        },
        {
          "id": "Koi Baat Chale (2023) Season 1 (Zee5)",
          "title": "Koi Baat Chale (2023) Season 1 (Zee5)",
          "poster": "https://m.media-amazon.com/images/M/MV5BY2MxZGQwMjctNzMyMC00MWZlLThkYzgtNjY0ZmI0MmJiZGY0XkEyXkFqcGdeQXVyMTEwMjI4NzYy._V1_FMjpg_UY576_.jpg",
          "stream_url": "https://jagur.ydc1wes.me/hls2/01/00004/iljnfdxawesy_,l,h,.urlset/master.m3u8?t=Z61BBaq6nTa2mgtXrlHLTWFid1jAoYJ4jfLoL_GRas8&s=1772484329&e=21600&f=24399&i=0.0&sp=0",
          "headers": {
            "Referer": "https://speedostream1.com/"
          }
        },
        {
          "id": "Taj: Divided by Blood (2023) Season 2 (Zee5)",
          "title": "Taj: Divided by Blood (2023) Season 2 (Zee5)",
          "poster": "https://www.themoviedb.org/t/p/w600_and_h900_bestv2/irf0ybJuUZ0YJFZiBWvxHXviCBU.jpg",
          "stream_url": "https://aamir.ydc1wes.me/hls2/01/00004/jh351r94zfob_,l,h,.urlset/master.m3u8?t=4CoFl_930ugL9nvS9TFmrGZcrZoAk-JIXoyVVlJ7SNs&s=1772484330&e=21600&f=23878&i=0.0&sp=0",
          "headers": {
            "Referer": "https://speedostream1.com/"
          }
        },
        {
          "id": "Sunflower (2021) Zee5 Original",
          "title": "Sunflower (2021) Zee5 Original",
          "poster": "https://m.media-amazon.com/images/M/MV5BYzI0ZmIzNmItMzVjMy00ZmNjLWFiMjAtMDY2OWQ3YmRiMjQ3XkEyXkFqcGdeQXVyMTIzMzg0MTM2._V1_FMjpg_UY720_.jpg",
          "stream_url": "https://aamir.ydc1wes.me/hls2/01/00006/tjzqmt4altwx_,l,h,.urlset/master.m3u8?t=xhGV5spK5NZduNy1ScpMXh87kKaGkA8nuwZfxSgH61M&s=1772484331&e=21600&f=30125&i=0.0&sp=0",
          "headers": {
            "Referer": "https://speedostream1.com/"
          }
        },
        {
          "id": "Abhay (2022) Season 3 Zee5",
          "title": "Abhay (2022) Season 3 Zee5",
          "poster": "https://m.media-amazon.com/images/M/MV5BZGI3NTI5YzgtNTNmMy00OTYwLWJlNmItNjc2ZmRiZWJiYTVmXkEyXkFqcGdeQXVyMTIyNzY0NTMx._V1_.jpg",
          "stream_url": "https://aamir.ydc1wes.me/hls2/01/00006/kw77p54iev6w_,l,h,.urlset/master.m3u8?t=IPor71Wgezo2AXJsZ-9Tccm5e7GyE6-zLd-h5E-8aL8&s=1772484331&e=21600&f=33572&i=0.0&sp=0",
          "headers": {
            "Referer": "https://speedostream1.com/"
          }
        },
        {
          "id": "Bus Stop (2019) Zee5 Hindi",
          "title": "Bus Stop (2019) Zee5 Hindi",
          "poster": "https://akamaividz2.zee5.com/image/upload/w_168,h_252,c_scale,f_auto,q_auto/resources/0-0-109641/portrait/busstop_1920x77_1127355387.jpg",
          "stream_url": "https://harduesx.ydc1wes.me/hls2/01/00004/ls9fjzc96022_,l,h,.urlset/master.m3u8?t=k9hcj0d39YpL5ze6mn7Os3ZInFvIufsnwGH7ATA8kK0&s=1772484332&e=21600&f=23091&i=0.0&sp=0",
          "headers": {
            "Referer": "https://speedostream1.com/"
          }
        },
        {
          "id": "Ayali (2023) Season 1 (Zee5)",
          "title": "Ayali (2023) Season 1 (Zee5)",
          "poster": "https://m.media-amazon.com/images/M/MV5BNzUwOWU0ZTUtNDdhNS00YWM4LThiYWYtMzhmYjhhNWRlNzc4XkEyXkFqcGdeQXVyMTIyNzY0NTMx._V1_FMjpg_UY576_.jpg",
          "stream_url": "https://jnaove.ydc1wes.me/hls2/02/00004/gnaibjhnlm7r_,l,h,.urlset/master.m3u8?t=hSZ8Krv_m6y1DIhpq_s4M0_MnGAF22rvV2jqR0ICjeA&s=1772484333&e=21600&f=23010&i=0.0&sp=0",
          "headers": {
            "Referer": "https://speedostream1.com/"
          }
        },
        {
          "id": "United Kacche (2023) Season 1 (Zee5)",
          "title": "United Kacche (2023) Season 1 (Zee5)",
          "poster": "https://m.media-amazon.com/images/M/MV5BZTkyNmYxODEtN2ExYi00YTYxLTk3ZDQtYWJjZmRhYjBlMzgwXkEyXkFqcGdeQXVyMTIyNzY0NTMx._V1_FMjpg_UY853_.jpg",
          "stream_url": "https://jesse.ydc1wes.me/hls2/02/00004/sc89lkrig5jq_,l,h,.urlset/master.m3u8?t=l0wplauFNy-xyKEZPB0vlBxIbasSfjPpzs886XZ0pN0&s=1772484334&e=21600&f=22835&i=0.0&sp=0",
          "headers": {
            "Referer": "https://speedostream1.com/"
          }
        },
        {
          "id": "Seven (2023) Season 1 (Zee5)",
          "title": "Seven (2023) Season 1 (Zee5)",
          "poster": "https://m.media-amazon.com/images/M/MV5BMzU1ZTExNzUtNThhZS00MTg0LWI5MDMtMGM2NWJkNmViMjIyXkEyXkFqcGdeQXVyMTIyNzY0NTMx._V1_FMjpg_UY576_.jpg",
          "stream_url": "https://dave.ydc1wes.me/hls2/02/00004/5m8ct7et9v5e_,l,h,.urlset/master.m3u8?t=up47bidFW3rnscnpe7IztmsN6KBYO_S5x7ZnP_8egC4&s=1772484335&e=21600&f=22706&i=0.0&sp=0",
          "headers": {
            "Referer": "https://speedostream1.com/"
          }
        },
        {
          "id": "Taj: Divided by Blood (2023) Season 1 (Zee5)",
          "title": "Taj: Divided by Blood (2023) Season 1 (Zee5)",
          "poster": "https://m.media-amazon.com/images/M/MV5BYjhhNGZmYzAtNmM4Mi00NjA4LTgxMGEtYWNjOTRhYzNiM2FlXkEyXkFqcGdeQXVyMTU4ODg1MTk2._V1_FMjpg_UY576_.jpg",
          "stream_url": "https://aamir.ydc1wes.me/hls2/01/00004/f6hl9kae1zsq_,l,h,.urlset/master.m3u8?t=UGks8S62Zl7EARkVKzbFcbI4b14fBWjSiCgEFi-UuSY&s=1772484336&e=21600&f=22139&i=0.0&sp=0",
          "headers": {
            "Referer": "https://speedostream1.com/"
          }
        },
        {
          "id": "Duranga (2022) Season 1 (Zee5)",
          "title": "Duranga (2022) Season 1 (Zee5)",
          "poster": "https://m.media-amazon.com/images/M/MV5BZGJkM2Q0NDMtM2YwYS00MDc1LTlhZDItMDk4Zjg2MzkwNDk2XkEyXkFqcGdeQXVyMTIyNzY0NTMx._V1_FMjpg_UY576_.jpg",
          "stream_url": "https://aamir.ydc1wes.me/hls2/01/00003/te0laa321iaz_,l,h,.urlset/master.m3u8?t=9QBee6ponHIW0Ja-ckltLYjzs1NjdIwxXlZRlYO7w4M&s=1772484336&e=21600&f=18243&i=0.0&sp=0",
          "headers": {
            "Referer": "https://speedostream1.com/"
          }
        },
        {
          "id": "Jaanbaaz Hindustan Ke (2023) Season 1 (Zee5)",
          "title": "Jaanbaaz Hindustan Ke (2023) Season 1 (Zee5)",
          "poster": "https://m.media-amazon.com/images/M/MV5BMDM2MzdhNWUtOWJlYS00ZGI4LWE4MmMtMTU2Mjk2NDdhYTE1XkEyXkFqcGdeQXVyMTIyNzY0NTMx._V1_FMjpg_UY853_.jpg",
          "stream_url": "https://aamir.ydc1wes.me/hls2/01/00004/tca8377i2t9z_,l,h,.urlset/master.m3u8?t=Ewqw7U_L6ai05GTCGy6Ad2KvYEsXaP8soQuh4EE9ms0&s=1772484337&e=21600&f=21351&i=0.0&sp=0",
          "headers": {
            "Referer": "https://speedostream1.com/"
          }
        },
        {
          "id": "Country Mafia (2022) Season 1 (Zee5)",
          "title": "Country Mafia (2022) Season 1 (Zee5)",
          "poster": "https://images.ottplay.com/posters/0badf3dc284ab54767122623976f0743.jpg",
          "stream_url": "https://aamir.ydc1wes.me/hls2/01/00003/u9znbwwzucbl_,l,h,.urlset/master.m3u8?t=JsyAncL_pvgczjxwdC_kgwJM6wMWPRhsPItHHlDpeOc&s=1772484338&e=21600&f=19835&i=0.0&sp=0",
          "headers": {
            "Referer": "https://speedostream1.com/"
          }
        },
        {
          "id": "Aha Na Pellanta (2022) Season 1 Hindi Dubbed Zee5 Original",
          "title": "Aha Na Pellanta (2022) Season 1 Hindi Dubbed Zee5 Original",
          "poster": "https://m.media-amazon.com/images/M/MV5BNGU3MjY2NzItNzY1Ny00NTY4LWFiMzctNWVkYjExNDFiNjExXkEyXkFqcGdeQXVyMTU2NDkwOTAw._V1_FMjpg_UY600_.jpg",
          "stream_url": "https://oldfils.ydc1wes.me/hls2/01/00003/et61a8c5vb0i_,l,h,.urlset/master.m3u8?t=VLJgoJ2NugNMYBS1Dbsfn4ssQmdTkXvIRt2QT8GZk5o&s=1772484339&e=21600&f=19808&i=0.0&sp=0",
          "headers": {
            "Referer": "https://speedostream1.com/"
          }
        },
        {
          "id": "Mukhbir – The Story of a Spy (2022) Season 1 (Zee5)",
          "title": "Mukhbir – The Story of a Spy (2022) Season 1 (Zee5)",
          "poster": "https://m.media-amazon.com/images/M/MV5BOTUzNzFmYTEtODYyMS00ZjAwLTgxMTQtY2E0YjQ3Y2MzNmM2XkEyXkFqcGdeQXVyMTIyNzY0NTMx._V1_FMjpg_UY853_.jpg",
          "stream_url": "https://aamir.ydc1wes.me/hls2/01/00003/dhsaj0zrsafe_,l,h,.urlset/master.m3u8?t=AgPl1l3sZ66COERvsZ6fGahH4ge54_rTAqnvu5NEmdI&s=1772484339&e=21600&f=19659&i=0.0&sp=0",
          "headers": {
            "Referer": "https://speedostream1.com/"
          }
        },
        {
          "id": "Ishq Pashmina (2022)",
          "title": "Ishq Pashmina (2022)",
          "poster": "https://m.media-amazon.com/images/M/MV5BMTkyMWIxYjMtYTE3OS00NmUxLThlZmItZjNhZjBiNjlmMzk1XkEyXkFqcGdeQXVyMTA3NTEyNzEz._V1_FMjpg_UY720_.jpg",
          "stream_url": "https://armantot.ydc1wes.me/hls2/01/00003/8tmbw2gv0vxb_,l,h,.urlset/master.m3u8?t=ef4MFArkmLqxg_AASezBTXyo-IM1YTizC6jg16VeyEE&s=1772484340&e=21600&f=18831&i=0.0&sp=0",
          "headers": {
            "Referer": "https://speedostream1.com/"
          }
        },
        {
          "id": "Rangbaaz – Darr Ki Rajneeti (2022) Season 1 (Zee5)",
          "title": "Rangbaaz – Darr Ki Rajneeti (2022) Season 1 (Zee5)",
          "poster": "https://m.media-amazon.com/images/M/MV5BNWZiMjI5MzktY2ExZS00MzIyLTg0YzUtY2NmYzk0MmJmNjYyXkEyXkFqcGdeQXVyMTIyNzY0NTMx._V1_FMjpg_UY600_.jpg",
          "stream_url": "https://dave.ydc1wes.me/hls2/01/00003/23kxf8gkwpm9_,l,h,.urlset/master.m3u8?t=2qF5_bpU4fIDLO09XdlXc8UKaiHP0W2NgVhQznVPE5E&s=1772484341&e=21600&f=17913&i=0.0&sp=0",
          "headers": {
            "Referer": "https://speedostream1.com/"
          }
        },
        {
          "id": "Kailasapuram (2019) Season 1 Hindi Dubbed Zee5 Original",
          "title": "Kailasapuram (2019) Season 1 Hindi Dubbed Zee5 Original",
          "poster": "https://m.media-amazon.com/images/M/MV5BYzlmMjA3NWItYWQ3YS00NmFkLTkwYzctZWJhNTZlNTI0NmRlXkEyXkFqcGdeQXVyMTEzMDMzMzUz._V1_FMjpg_UY681_.jpg",
          "stream_url": "https://dave.ydc1wes.me/hls2/01/00003/ynvay40kol2l_,l,h,.urlset/master.m3u8?t=4BEm0HEDvccMZHgHLfLFfxRBo5rrYUNxp7MlXbXUydA&s=1772484342&e=21600&f=17525&i=0.0&sp=0",
          "headers": {
            "Referer": "https://speedostream1.com/"
          }
        },
        {
          "id": "Sass Meri Ne Munda Jameya (2022) Punjabi",
          "title": "Sass Meri Ne Munda Jameya (2022) Punjabi",
          "poster": "https://bingeddata.s3.amazonaws.com/uploads/2022/06/Sass-Meri-Ne-Munda-Jameya-Punjabi-Movie-Streaming-Online-Watch.jpg",
          "stream_url": "https://aamir.ydc1wes.me/hls2/01/00003/fa72vy41m2b5_,l,o,.urlset/master.m3u8?t=NivVZLNX-Hfj-MMlTrZxCs9zpzTp8XFsru5C_BjUpt4&s=1772484343&e=21600&f=17180&i=0.0&sp=0",
          "headers": {
            "Referer": "https://speedostream1.com/"
          }
        },
        {
          "id": "The Broken News (2022) Season 1 (Zee5)",
          "title": "The Broken News (2022) Season 1 (Zee5)",
          "poster": "https://m.media-amazon.com/images/M/MV5BZTg5YjMwMzgtMzgwNy00NDY5LTkwYTYtYmU1OWYxNDAyZTY1XkEyXkFqcGdeQXVyMTIyNzY0NTMx._V1_FMjpg_UY600_.jpg",
          "stream_url": "https://aamir.ydc1wes.me/hls2/01/00003/vjwgpmr1v2hs_,l,o,.urlset/master.m3u8?t=75INazqlaVvQW3QShM5qb1TdouJfrigLCzPQYPcqgwE&s=1772484344&e=21600&f=17075&i=0.0&sp=0",
          "headers": {
            "Referer": "https://speedostream1.com/"
          }
        },
        {
          "id": "Never Kiss Your Best Friend (2022) Season 2 Zee5",
          "title": "Never Kiss Your Best Friend (2022) Season 2 Zee5",
          "poster": "https://m.media-amazon.com/images/M/MV5BZDNlNmUwYzUtMWQ1YS00YTRjLWIxN2QtNzdjN2YyNjdmMzU5XkEyXkFqcGdeQXVyMTIyNzY0NTMx._V1_.jpg",
          "stream_url": "https://gustavo.ydc1wes.me/hls2/02/00003/f85j0ghcje1j_,l,o,.urlset/master.m3u8?t=zL7JMUvhad_htgTGHzCgaKpqdeJIkX9ojKr2GImlHj8&s=1772484345&e=21600&f=16379&i=0.0&sp=0",
          "headers": {
            "Referer": "https://speedostream1.com/"
          }
        },
        {
          "id": "Anantham (2022) Season 1 Hindi Dubbed Zee5 Original",
          "title": "Anantham (2022) Season 1 Hindi Dubbed Zee5 Original",
          "poster": "https://www.themoviedb.org/t/p/w600_and_h900_bestv2/vJsOALYO7xl984eFPSa8gD37row.jpg",
          "stream_url": "https://arabic.ydc1wes.me/hls2/01/00003/z3guap24l76x_,l,o,.urlset/master.m3u8?t=BsFciwaniTE5Y0_hWqaCW3PIJ1IwgphNXLIRYGXEx8A&s=1772484346&e=21600&f=16302&i=0.0&sp=0",
          "headers": {
            "Referer": "https://speedostream1.com/"
          }
        },
        {
          "id": "Bloody Brothers (2022) Season 1 Zee5 Original",
          "title": "Bloody Brothers (2022) Season 1 Zee5 Original",
          "poster": "https://m.media-amazon.com/images/M/MV5BNzFlMTJmMzEtOGU4Yy00NzYyLTkxY2QtZGE1MzJlNjVjZTFiXkEyXkFqcGdeQXVyMTIyNzY0NTMx._V1_FMjpg_UY720_.jpg",
          "stream_url": "https://aamir.ydc1wes.me/hls2/01/00003/gjnejm8uo8dk_,l,o,.urlset/master.m3u8?t=G2jtNppvotlcQt322g_VkgGVr8WnP8BHPsLZfdzfxmA&s=1772484347&e=21600&f=15870&i=0.0&sp=0",
          "headers": {
            "Referer": "https://speedostream1.com/"
          }
        },
        {
          "id": "Sutliyan (2022) Season 1 Zee5 Original",
          "title": "Sutliyan (2022) Season 1 Zee5 Original",
          "poster": "https://m.media-amazon.com/images/M/MV5BNjM3NWEzZDgtOTE0Mi00MGI1LWFjMTMtMTI1YTM2NDY5NzMzXkEyXkFqcGdeQXVyMTIzMzg0MTM2._V1_FMjpg_UY720_.jpg",
          "stream_url": "https://jnaove.ydc1wes.me/hls2/02/00003/1ct0ecbywbrv_,l,o,.urlset/master.m3u8?t=xxsHOAOpT8KeAMT4HpXp9ptNWNzcVgItxwXDzZRn854&s=1772484348&e=21600&f=15655&i=0.0&sp=0",
          "headers": {
            "Referer": "https://speedostream1.com/"
          }
        },
        {
          "id": "Benwad (2022)",
          "title": "Benwad (2022)",
          "poster": "https://ingfree.xyz/ib/B5TGbJbLJQ.png",
          "stream_url": "https://jnaove.ydc1wes.me/hls2/02/00003/0wuakbh37ubw_,l,o,.urlset/master.m3u8?t=jqsaSCVeu3EbmA_JdrIjX-CsT7OHxWn4ffXBraDHjy8&s=1772484349&e=21600&f=15466&i=0.0&sp=0",
          "headers": {
            "Referer": "https://speedostream1.com/"
          }
        },
        {
          "id": "Pavitra Rishta Its Never Too Late (2022) Season 2 Zee5 Original",
          "title": "Pavitra Rishta Its Never Too Late (2022) Season 2 Zee5 Original",
          "poster": "https://m.media-amazon.com/images/M/MV5BMGM1NjI0NDEtNDg3Ni00ZmE2LWI5NDUtNjMxN2VlMWVlZTNjXkEyXkFqcGdeQXVyMTIzMzg0MTM2._V1_FMjpg_UX1024_.jpg",
          "stream_url": "https://jnaove.ydc1wes.me/hls2/02/00003/zf0ppf5iz57g_,l,o,.urlset/master.m3u8?t=ndAsule8WdxEuTjA8qD0KV_kIesVHuUGLwX0Cy1KfMA&s=1772484350&e=21600&f=15194&i=0.0&sp=0",
          "headers": {
            "Referer": "https://speedostream1.com/"
          }
        },
        {
          "id": "Kaun Banegi Shikharwati (2022) Season 1 Zee5 Original",
          "title": "Kaun Banegi Shikharwati (2022) Season 1 Zee5 Original",
          "poster": "https://m.media-amazon.com/images/M/MV5BYjUwM2M5NTEtZjA3Yy00M2MyLWE3MDgtZmZkZTdkNjIzNDNiXkEyXkFqcGdeQXVyMTIzMzg0MTM2._V1_FMjpg_UY720_.jpg",
          "stream_url": "https://dawn.ydc1wes.me/hls2/02/00002/yplq1cdezls6_,l,o,.urlset/master.m3u8?t=Fudc_KiJRmxvL7KoaUGBEcfNVvoW4pd6tS_FtjIMURA&s=1772484351&e=21600&f=15305&i=0.0&sp=0",
          "headers": {
            "Referer": "https://speedostream1.com/"
          }
        },
        {
          "id": "Qatil Haseenaon Ke Naam (2021) Season 1 Zee5 Original",
          "title": "Qatil Haseenaon Ke Naam (2021) Season 1 Zee5 Original",
          "poster": "https://m.media-amazon.com/images/M/MV5BOTQ5ZTExZjktYjg5MC00NGMzLTk4ZmUtMGZmZmNkZTAyNzdhXkEyXkFqcGdeQXVyMTIzMzg0MTM2._V1_FMjpg_UX630_.jpg",
          "stream_url": "https://jnaove.ydc1wes.me/hls2/02/00002/e4dc3sw8nygq_,l,o,.urlset/master.m3u8?t=SUgT_gcQ-lpriApj6_zemy48izhy562x3t-WE1mILnA&s=1772484352&e=21600&f=14661&i=0.0&sp=0",
          "headers": {
            "Referer": "https://speedostream1.com/"
          }
        },
        {
          "id": "Glitter (2021) Season 1 Zee5 Original",
          "title": "Glitter (2021) Season 1 Zee5 Original",
          "poster": "https://akamaividz2.zee5.com/image/upload/w_630,h_945,c_scale,f_webp,q_auto:eco/resources/0-6-4z517059/portrait/1920x7709abac683ba1546f48231f067b85e8ff6.jpg",
          "stream_url": "https://jnaove.ydc1wes.me/hls2/02/00002/c6bbl1ew2szi_l/master.m3u8?t=Bxi1H3PmJQdeIRnlmQUjeHPtacNOpA_21vXxSpLl8YQ&s=1772484352&e=21600&f=15616&i=0.0&sp=0",
          "headers": {
            "Referer": "https://speedostream1.com/"
          }
        },
        {
          "id": "Raid (2019) Season 1 Zee5 Original",
          "title": "Raid (2019) Season 1 Zee5 Original",
          "poster": "https://m.media-amazon.com/images/M/MV5BNzQxZmUxYzktZTY3Yy00NjQ5LTgzNjItOThmZjk3MjZmMzQ3XkEyXkFqcGdeQXVyNDIwNjc3NDY@._V1_FMjpg_UX1000_.jpg",
          "stream_url": "https://jnaove.ydc1wes.me/hls2/02/00002/3rr2w1pubnrz_,l,o,.urlset/master.m3u8?t=OWsZT4PEY98Tl2NVlnmuCbdQSAaSSfOeDmueyUehCOg&s=1772484353&e=21600&f=12993&i=0.0&sp=0",
          "headers": {
            "Referer": "https://speedostream1.com/"
          }
        },
        {
          "id": "Luv Kushh (2021) Season 1",
          "title": "Luv Kushh (2021) Season 1",
          "poster": "https://m.media-amazon.com/images/M/MV5BOTJiYTI5MmYtMzZiMi00NjdiLWIyMWYtNDUxMjJmYWZhNWU2XkEyXkFqcGdeQXVyNTM3MDMyMDQ@._V1_FMjpg_UX375_.jpg",
          "stream_url": "https://jnaove.ydc1wes.me/hls2/02/00002/p4ki6o7o2st5_,l,o,.urlset/master.m3u8?t=FJDfyNzf_lyhy5Bme0pVoo-rx5Gle5gh-QqVxUmTfeU&s=1772484355&e=21600&f=12448&i=0.0&sp=0",
          "headers": {
            "Referer": "https://speedostream1.com/"
          }
        },
        {
          "id": "Engineering Girls (2021) Season 2 Zee5 Original",
          "title": "Engineering Girls (2021) Season 2 Zee5 Original",
          "poster": "https://m.media-amazon.com/images/M/MV5BMzE0NGZhYTktYzM2Yy00MWJlLWIyODUtMWRmY2ExYjMwZjI3XkEyXkFqcGdeQXVyNDY4NjAxNTc@._V1_FMjpg_UY720_.jpg",
          "stream_url": "https://jnaove.ydc1wes.me/hls2/02/00002/fjcg52ofq6w8_,l,o,.urlset/master.m3u8?t=5ovW9uhTUgwMqXGfSdAlbjs64eqrcnPhxwxulOwnWaA&s=1772484356&e=21600&f=15588&i=0.0&sp=0",
          "headers": {
            "Referer": "https://speedostream1.com/"
          }
        },
        {
          "id": "Engineering Girls (2021) Season 1 Zee5 Original",
          "title": "Engineering Girls (2021) Season 1 Zee5 Original",
          "poster": "https://m.media-amazon.com/images/M/MV5BODkwMmIwYjMtYzY2ZC00N2E2LTkyNmUtZjUyMjVhYzE4NmQxXkEyXkFqcGdeQXVyNDAzNDk0MTQ@._V1_FMjpg_UY720_.jpg ",
          "stream_url": "https://jnaove.ydc1wes.me/hls2/02/00002/4xe23v01qnw6_,l,o,.urlset/master.m3u8?t=WUVoWrxiq6X4aARC-ZotQZ0bKCFUVu8oYQOQVsRHhSU&s=1772484357&e=21600&f=12043&i=0.0&sp=0",
          "headers": {
            "Referer": "https://speedostream1.com/"
          }
        },
        {
          "id": "Badnaam (2021) Season 1 Zee5 Original",
          "title": "Badnaam (2021) Season 1 Zee5 Original",
          "poster": "https://akamaividz2.zee5.com/image/upload/w_630,h_945,c_scale,f_webp,q_auto:eco/resources/0-0-1z51361/portrait/1920x77041f2aab227b148cdb126557ef16ac289.jpg",
          "stream_url": "https://jnaove.ydc1wes.me/hls2/02/00002/pqiinm32qa0g_,l,o,.urlset/master.m3u8?t=q9ybRDnLLjxpdhJXRxl6kBIynwHvT-jF212RvzRSBwE&s=1772484358&e=21600&f=12004&i=0.0&sp=0",
          "headers": {
            "Referer": "https://speedostream1.com/"
          }
        },
        {
          "id": "Dhoop Ki Deewar (2021) Season 1 Zee5 Original",
          "title": "Dhoop Ki Deewar (2021) Season 1 Zee5 Original",
          "poster": "https://m.media-amazon.com/images/M/MV5BNWYwYWU2NDUtZGZjOC00OTNlLTkzNjEtZGZkYWI4NDBlNzc1XkEyXkFqcGdeQXVyMTIzMzg0MTM2._V1_FMjpg_UX818_.jpg",
          "stream_url": "https://jnaove.ydc1wes.me/hls2/02/00002/as319n6at69z_,l,o,.urlset/master.m3u8?t=LdLpO8uSr_vKcW5Tx9Zh0xAJ2yV2OcFI8GlK8tT6_0U&s=1772484359&e=21600&f=15587&i=0.0&sp=0",
          "headers": {
            "Referer": "https://speedostream1.com/"
          }
        },
        {
          "id": "Raat Baaki Hai (2021) Season 1 Zee5",
          "title": "Raat Baaki Hai (2021) Season 1 Zee5",
          "poster": "https://m.media-amazon.com/images/M/MV5BMGQ5NDE5MzQtZDkxMS00OTIyLTkyNDctOTRiNWZhODE5MThiXkEyXkFqcGdeQXVyMTI1NDAzMzM0._V1_FMjpg_UX909_.jpg",
          "stream_url": "https://jnaove.ydc1wes.me/hls2/02/00001/m7t61nujbti7_,l,o,.urlset/master.m3u8?t=lRBWPsirFyabnYZ9f6FNuj0occW3VhiWj-GusMlHkYg&s=1772484360&e=21600&f=14234&i=0.0&sp=0",
          "headers": {
            "Referer": "https://speedostream1.com/"
          }
        },
        {
          "id": "Horn Ok Please (2018) Season 1 Zee5",
          "title": "Horn Ok Please (2018) Season 1 Zee5",
          "poster": "https://m.media-amazon.com/images/M/MV5BMWU1MTdmMmItZGZiZi00MzU0LThjYzEtZmQ0ZmVkMGM0YWExXkEyXkFqcGdeQXVyMjUxMTY3ODM@._V1_FMjpg_UY853_.jpg",
          "stream_url": "https://jnaove.ydc1wes.me/hls2/02/00001/ma7asu3axdcs_,l,o,.urlset/master.m3u8?t=dgFphKgbZqo4EvJuY4qGB-8Lf4bAb15Jed4nnuh31CY&s=1772484361&e=21600&f=7383&i=0.0&sp=0",
          "headers": {
            "Referer": "https://speedostream1.com/"
          }
        },
        {
          "id": "RejctX (2019) Season 2 Zee5",
          "title": "RejctX (2019) Season 2 Zee5",
          "poster": "https://m.media-amazon.com/images/M/MV5BOTc1MzdlMDktYjExYi00ZjMzLTllNzEtZWI5ZGYzOGY4ZDJhXkEyXkFqcGdeQXVyMjUxMTY3ODM@._V1_FMjpg_UY480_.jpg",
          "stream_url": "https://jnaove.ydc1wes.me/hls2/02/00001/oi7rhjgb3odn_,l,o,.urlset/master.m3u8?t=_9IzerLRkw_VS02qtUk2cqhde1E86Ge2vUCG02cd1LA&s=1772484362&e=21600&f=7276&i=0.0&sp=0",
          "headers": {
            "Referer": "https://speedostream1.com/"
          }
        },
        {
          "id": "Akoori (2018) Zee5",
          "title": "Akoori (2018) Zee5",
          "poster": "https://m.media-amazon.com/images/M/MV5BYmRhMTAxMTQtNzJhNC00NzZjLThmZjctYzBkZTJmOWFlOTg5XkEyXkFqcGdeQXVyODk0ODg2MzM@._V1_FMjpg_UX1074_.jpg",
          "stream_url": "https://jnaove.ydc1wes.me/hls2/02/00000/nx1g5s30w236_,l,o,.urlset/master.m3u8?t=cLZQREPE0VCRPpRRhKhNct-j-Wc5O2kC4NEltEXyD3s&s=1772484363&e=21600&f=1892&i=0.0&sp=0",
          "headers": {
            "Referer": "https://speedostream1.com/"
          }
        },
        {
          "id": "Mee Raqsam (2020)",
          "title": "Mee Raqsam (2020)",
          "poster": "https://m.media-amazon.com/images/M/MV5BMWVmYjQ3M2ItNDJjNC00MjJjLTk3MmEtYWZhOWE2MTQ5ZTYwXkEyXkFqcGdeQXVyMTIxMjE2NzIz._V1_.jpg",
          "stream_url": "https://harduesx.ydc1wes.me/hls2/01/00000/h8rhwvfbqqc4_,l,o,.urlset/master.m3u8?t=58tSwYKvxoE011ik_eKtPSYv2rhuz8OOl-pCiuKJ1Fs&s=1772484366&e=21600&f=14267&i=0.0&sp=0",
          "headers": {
            "Referer": "https://speedostream1.com/"
          }
        },
        {
          "id": "Badalte Chehre (2018) Season 1 Zee5",
          "title": "Badalte Chehre (2018) Season 1 Zee5",
          "poster": "https://m.media-amazon.com/images/M/MV5BNzNkOTIwNDMtNjc0MS00YzM1LWI4YzQtMjhlZTRiMzAxOTNmXkEyXkFqcGdeQXVyNjA2ODk4OTM@._V1_FMjpg_UX606_.jpg",
          "stream_url": "https://harduesx.ydc1wes.me/hls2/01/00001/ob20bfjmnsas_,l,o,.urlset/master.m3u8?t=v1tg8KRwN5yS7rrw760n6VsGh6DtuXLpptg-zmKa14M&s=1772484367&e=21600&f=15609&i=0.0&sp=0",
          "headers": {
            "Referer": "https://speedostream1.com/"
          }
        },
        {
          "id": "Qubool Hai 2.0 (2021) Season 1 Zee5",
          "title": "Qubool Hai 2.0 (2021) Season 1 Zee5",
          "poster": "https://m.media-amazon.com/images/M/MV5BMjJlMjhhZmUtZTNmNC00NTU5LWFkNmQtN2QyNzNjOTBhYjk2XkEyXkFqcGdeQXVyMTI1NDAzMzM0._V1_FMjpg_UX1080_.jpg",
          "stream_url": "https://jnaove.ydc1wes.me/hls2/02/00001/0r4gl6s3jef0_,l,o,.urlset/master.m3u8?t=ilX0G6YUfbA42u2TNPEfGANkKktLc6YtpLY_I36EgHY&s=1772484368&e=21600&f=6475&i=0.0&sp=0",
          "headers": {
            "Referer": "https://speedostream1.com/"
          }
        },
        {
          "id": "Rangbaaz (2018) Season 1 Zee5",
          "title": "Rangbaaz (2018) Season 1 Zee5",
          "poster": "https://m.media-amazon.com/images/M/MV5BZDU1M2YyZmQtYmFhOC00ODk0LTg5YzktYjA2YWY5MWM0ODM0XkEyXkFqcGdeQXVyMjUxMTY3ODM@._V1_SY1000_CR0,0,686,1000_AL_.jpg",
          "stream_url": "https://jagur.ydc1wes.me/hls2/01/00000/4s4jg8uiih6u_,l,o,.urlset/master.m3u8?t=qgV8tpziiSlLybMMsJe9yKFvxQsP7sKMsa3_37fa40Q&s=1772484369&e=21600&f=4745&i=0.0&sp=0",
          "headers": {
            "Referer": "https://speedostream1.com/"
          }
        },
        {
          "id": "Jamai 2.0 (2021) Season 2 Zee5",
          "title": "Jamai 2.0 (2021) Season 2 Zee5",
          "poster": "https://m.media-amazon.com/images/M/MV5BZjBkMTZhNzMtOWUzYy00NGQ0LTgzMWItMzFhNDVlNGE1Y2Y3XkEyXkFqcGdeQXVyMTI1NDAzMzM0._V1_FMjpg_UX1080_.jpg",
          "stream_url": "https://gustavo.ydc1wes.me/hls2/01/00001/5ajk7fy5bmfr_,l,o,.urlset/master.m3u8?t=Nem9TYzSbzsKyPBIUUGsfvCiN6kg6cQDXUIUrKXzkOs&s=1772484370&e=21600&f=6021&i=0.0&sp=0",
          "headers": {
            "Referer": "https://speedostream1.com/"
          }
        },
        {
          "id": "Chintu Ka Birthday (2020)",
          "title": "Chintu Ka Birthday (2020)",
          "poster": "https://m.media-amazon.com/images/M/MV5BNDg2OGIzYWQtY2MyZC00MDM0LWFiNWItZWMxOWFlY2Q5Nzg3XkEyXkFqcGdeQXVyMzQ5Njc3NzU@._V1_QL50_.jpg",
          "stream_url": "https://harduesx.ydc1wes.me/hls2/01/00000/tuccnr0xwtun_,l,o,.urlset/master.m3u8?t=v1A48bwAaEoHiF_tQt5Z9DTmr3Pe30ySSfuRNRd7NEQ&s=1772484371&e=21600&f=15596&i=0.0&sp=0",
          "headers": {
            "Referer": "https://speedostream1.com/"
          }
        },
        {
          "id": "Meka Suri 2 (2021) Season 1 Zee5",
          "title": "Meka Suri 2 (2021) Season 1 Zee5",
          "poster": "https://www.themoviedb.org/t/p/w600_and_h900_bestv2/gXAVuWQ7BDyKcPCtbu3iiStDDhR.jpg",
          "stream_url": "https://jnaove.ydc1wes.me/hls2/02/00001/3hhcbt2t5xjo_,l,o,.urlset/master.m3u8?t=Y9Jd5UHvrZQEvGgchdxqyiZJlchS4BMK2x6fH1mN6xk&s=1772484371&e=21600&f=5640&i=0.0&sp=0",
          "headers": {
            "Referer": "https://speedostream1.com/"
          }
        },
        {
          "id": "Fingertip (2019) Season 1 Hindi Dubbed Zee5",
          "title": "Fingertip (2019) Season 1 Hindi Dubbed Zee5",
          "poster": "https://m.media-amazon.com/images/M/MV5BOWIxMWNjMjktZmMwOS00YzZiLTgxMTUtZGJiYTMwM2VhYzc2XkEyXkFqcGdeQXVyMTAwMTU3MTY2._V1_FMjpg_UY1280_.jpg",
          "stream_url": "https://harduesx.ydc1wes.me/hls2/01/00001/dc0cywbr464r_,l,o,.urlset/master.m3u8?t=kH__rovez0Y3AJD9qsIvtqALvXPrKLOYd55VSOwADyE&s=1772484372&e=21600&f=14254&i=0.0&sp=0",
          "headers": {
            "Referer": "https://speedostream1.com/"
          }
        },
        {
          "id": "Codename Gondya (2019) Season 1 Hindi Dubbed",
          "title": "Codename Gondya (2019) Season 1 Hindi Dubbed",
          "poster": "https://m.media-amazon.com/images/M/MV5BNjc0ZTBmYTUtMDM3Mi00NGMxLWFlN2YtNjBiNmE5NDY4MGIyXkEyXkFqcGdeQXVyMzYyNjUyODE@._V1_FMjpg_UY1280_.jpg",
          "stream_url": "https://harduesx.ydc1wes.me/hls2/01/00001/584bl9lktosa_,l,o,.urlset/master.m3u8?t=qU8CE1StJPxGb-qG_bwkImSteQqsHj6XN7LGBI2Dyus&s=1772484373&e=21600&f=5144&i=0.0&sp=0",
          "headers": {
            "Referer": "https://speedostream1.com/"
          }
        },
        {
          "id": "Ishq Aaj Kal (2019) Season 3 Zee5",
          "title": "Ishq Aaj Kal (2019) Season 3 Zee5",
          "poster": "https://www.themoviedb.org/t/p/w600_and_h900_bestv2/rP5v24WDAyXKC42V0gJuI1bE8tE.jpg",
          "stream_url": "https://jnaove.ydc1wes.me/hls2/02/00001/g64jaii4qm9z_,l,o,.urlset/master.m3u8?t=CiMQCvXQpoo0IYhZpXa_XcmLARsIIwB6IGKKDWG2opI&s=1772484374&e=21600&f=5087&i=0.0&sp=0",
          "headers": {
            "Referer": "https://speedostream1.com/"
          }
        },
        {
          "id": "Nisha (2019) Season 1 Zee5",
          "title": "Nisha (2019) Season 1 Zee5",
          "poster": "https://m.media-amazon.com/images/M/MV5BNjE4Y2Q5MTUtZGEyMS00NjIxLWJkNDAtOTgwNGRhMDY5NDVjXkEyXkFqcGdeQXVyMTE3MzczNTc4._V1_FMjpg_UX630_.jpg",
          "stream_url": "https://jagur.ydc1wes.me/hls2/01/00001/pthab3u2q433_,l,o,.urlset/master.m3u8?t=JYMkcDThfnJ2BvGS6rM94p_T_yTjRtA_Be2ZONIFQCU&s=1772484375&e=21600&f=5005&i=0.0&sp=0",
          "headers": {
            "Referer": "https://speedostream1.com/"
          }
        },
        {
          "id": "Jeet Ki Zid (2021) Season 1 Zee5",
          "title": "Jeet Ki Zid (2021) Season 1 Zee5",
          "poster": "https://m.media-amazon.com/images/M/MV5BZDNlN2E5NzEtYTZmNC00OGUyLTk1NTEtZmIzZDhhOGZhZTE5XkEyXkFqcGdeQXVyMTIzMzg0MTM2._V1_FMjpg_UX1080_.jpg",
          "stream_url": "https://aamir.ydc1wes.me/hls2/01/00000/5bzcqvs64jl6_,l,o,.urlset/master.m3u8?t=bjsDE2rk1UhzWOBFHikSIKXJj1dptD5vVQkd2h0En-c&s=1772484376&e=21600&f=4902&i=0.0&sp=0",
          "headers": {
            "Referer": "https://speedostream1.com/"
          }
        },
        {
          "id": "Bicchoo Ka Khel (2020) Season 1 (AltBalaji)",
          "title": "Bicchoo Ka Khel (2020) Season 1 (AltBalaji)",
          "poster": "https://m.media-amazon.com/images/M/MV5BN2Y2ZGQwNjUtMTBkNC00NzA5LWE3MTYtYTAxNWM3MzYxZjk2XkEyXkFqcGdeQXVyODI2MzM0MTM@._V1_FMjpg_UY887_.jpg",
          "stream_url": "https://aamir.ydc1wes.me/hls2/01/00000/shuu9c4q8cr1_,l,o,.urlset/master.m3u8?t=ZL3fnX4IyHUxtEN7dqaYHOvAh5Pl3Tb5b0uzyYG0oc8&s=1772484377&e=21600&f=15581&i=0.0&sp=0",
          "headers": {
            "Referer": "https://speedostream1.com/"
          }
        },
        {
          "id": "Rangbaaz Phirse (2019) Season 2 Zee5",
          "title": "Rangbaaz Phirse (2019) Season 2 Zee5",
          "poster": "https://m.media-amazon.com/images/M/MV5BYzRiNGEwOTEtM2I0OS00NWVmLWI5NWItNTFkYzFjMWIwYmNkXkEyXkFqcGdeQXVyOTQyODQ3NjM@._V1_QL50_.jpg",
          "stream_url": "https://jagur.ydc1wes.me/hls2/01/00000/gl6buv48i8x8_,l,o,.urlset/master.m3u8?t=U3tfkJFhBGhK37opEav0wMx8aSfm3OcRN_eIPvkgkQU&s=1772484378&e=21600&f=4746&i=0.0&sp=0",
          "headers": {
            "Referer": "https://speedostream1.com/"
          }
        },
        {
          "id": "Gods Of Dharmapuri (G.O.D) Season 1 Hindi Dubbed",
          "title": "Gods Of Dharmapuri (G.O.D) Season 1 Hindi Dubbed",
          "poster": "https://akamaividz2.zee5.com/image/upload/w_630,h_945,c_scale,f_auto,q_auto/resources/0-6-2132/portrait/1920x770_568665051.jpg",
          "stream_url": "https://gustavo.ydc1wes.me/hls2/01/00000/0vnv2jjlx2o3_,l,o,.urlset/master.m3u8?t=K99qxpevo78MKvhq7pm6MF5efaqGm_-9nqBGA8FspAU&s=1772484379&e=21600&f=4682&i=0.0&sp=0",
          "headers": {
            "Referer": "https://speedostream1.com/"
          }
        },
        {
          "id": "Never Kiss Your Best Friend (2020) Season 1",
          "title": "Never Kiss Your Best Friend (2020) Season 1",
          "poster": "https://m.media-amazon.com/images/M/MV5BZDNlNmUwYzUtMWQ1YS00YTRjLWIxN2QtNzdjN2YyNjdmMzU5XkEyXkFqcGdeQXVyMTIyNzY0NTMx._V1_FMjpg_UY600_.jpg",
          "stream_url": "https://jesse.ydc1wes.me/hls2/01/00000/swh8rqk96za1_,l,n,.urlset/master.m3u8?t=gFj69hsxAW33zBlACATa3Jg7NCiy1_mc8vMZi7ETFEA&s=1772484380&e=21600&f=1440&i=0.0&sp=0",
          "headers": {
            "Referer": "https://speedostream1.com/"
          }
        },
        {
          "id": "Poison (2020) Season 1 Zee5 Originals Series",
          "title": "Poison (2020) Season 1 Zee5 Originals Series",
          "poster": "https://m.media-amazon.com/images/M/MV5BZmY3MTk0MDItYThjOS00OTBhLTk3NmQtYjU0Zjc5M2U1ZDIwXkEyXkFqcGdeQXVyODE5NzE3OTE@._V1_QL50_SX692_CR0,0,692,999_AL_.jpg",
          "stream_url": "https://pinkman.ydc1wes.me/hls2/01/00000/eji4nkmqcccr_,l,o,.urlset/master.m3u8?t=3FSng5RhWEo1loWwtRZRKSahEX1tNhPRCt-M1TPX4lE&s=1772484381&e=21600&f=2493&i=0.0&sp=0",
          "headers": {
            "Referer": "https://speedostream1.com/"
          }
        },
        {
          "id": "Black Widows (2020) Season 1 Zee5",
          "title": "Black Widows (2020) Season 1 Zee5",
          "poster": "https://m.media-amazon.com/images/M/MV5BNmM0YWMwNDktODVmMy00MmJhLTg4OWMtOTMwNzBjYmQxMjFlXkEyXkFqcGdeQXVyMTIzMzg0MTM2._V1_FMjpg_UX630_.jpg",
          "stream_url": "https://jnaove.ydc1wes.me/hls2/02/00000/s45dv8yv77hv_,l,o,.urlset/master.m3u8?t=G6oGN875LP8KAG0fqshl0ZXR9YL7qzBJiWNz4Zb6P64&s=1772484381&e=21600&f=3996&i=0.0&sp=0",
          "headers": {
            "Referer": "https://speedostream1.com/"
          }
        },
        {
          "id": "Naxalbari (2020) Season 1 Zee5",
          "title": "Naxalbari (2020) Season 1 Zee5",
          "poster": " https://m.media-amazon.com/images/M/MV5BYmYyMDFiOTgtMzkwOS00OTU1LTg5OGItM2Q5MjcyNzc5MDJkXkEyXkFqcGdeQXVyMTI2MDYzMjc5._V1_FMjpg_UX913_.jpg",
          "stream_url": "https://jnaove.ydc1wes.me/hls2/02/00004/ivat7iathghl_,l,h,.urlset/master.m3u8?t=wvBsstgl_hgh9Bw7bhT3fqCk7Kuh9UgsoAVOjt7Fqlw&s=1772484382&e=21600&f=21935&i=0.0&sp=0",
          "headers": {
            "Referer": "https://speedostream1.com/"
          }
        },
        {
          "id": "Dark 7 White (2020) Season 1 Zee5",
          "title": "Dark 7 White (2020) Season 1 Zee5",
          "poster": "https://m.media-amazon.com/images/M/MV5BYjExNTgwNTItZmQxNC00MTBjLWFiYjAtMTQ1ODIyMTc3MzljXkEyXkFqcGdeQXVyMTIzMzg0MTM2._V1_FMjpg_UY1280_.jpg",
          "stream_url": "https://jnaove.ydc1wes.me/hls2/02/00000/1r4c0yycv6oa_,l,o,.urlset/master.m3u8?t=qmOslGaPWsS6Hg7RXh_enEjlDek_d9J3oJOIH-aTkEQ&s=1772484383&e=21600&f=15580&i=0.0&sp=0",
          "headers": {
            "Referer": "https://speedostream1.com/"
          }
        },
        {
          "id": "NERD: Neither Either Really Dead (2019) Season 1 Hindi Dubbed Zee5",
          "title": "NERD: Neither Either Really Dead (2019) Season 1 Hindi Dubbed Zee5",
          "poster": "https://akamaividz2.zee5.com/image/upload/w_504,h_756,c_scale,f_webp,q_auto:eco/resources/0-6-1876/portrait/1920x7701472095050.jpg",
          "stream_url": "https://fringe.ydc1wes.me/hls2/01/00001/r747tr4pvo6g_,l,o,.urlset/master.m3u8?t=46_RYLAzx7rJVczkLfd6ojp_03SG7790UBqxgBvC2Tc&s=1772484384&e=21600&f=9164&i=0.0&sp=0",
          "headers": {
            "Referer": "https://speedostream1.com/"
          }
        },
        {
          "id": "Ek Jhoothi Love Story (2020) ZEE5 Originals Web Series",
          "title": "Ek Jhoothi Love Story (2020) ZEE5 Originals Web Series",
          "poster": "https://m.media-amazon.com/images/M/MV5BY2JiZmY3MGUtOTg0MC00YTE3LWE1MjItZmM5YjZlNDE1ZjE5XkEyXkFqcGdeQXVyNjM3NjA2OTI@._V1_FMjpg_UY886_.jp",
          "stream_url": "https://jnaove.ydc1wes.me/hls2/02/00000/6lk3tibdi4gy_,l,o,.urlset/master.m3u8?t=rBfmK-RaRedil64y6-s88c2_IsjnP8yrM0H7zakwPhY&s=1772484385&e=21600&f=15591&i=0.0&sp=0",
          "headers": {
            "Referer": "https://speedostream1.com/"
          }
        },
        {
          "id": "Taish (2020) ZEE5 Originals Web Series",
          "title": "Taish (2020) ZEE5 Originals Web Series",
          "poster": "https://m.media-amazon.com/images/M/MV5BYzUwNzg4YjUtYjk4ZS00ZDJiLTk3ZmUtMDBkM2FjYjY0NWQ3XkEyXkFqcGdeQXVyMTIzMzg0MTM2._V1_FMjpg_UY1280_.jpg",
          "stream_url": "https://aamir.ydc1wes.me/hls2/01/00000/toirzlncadfy_,l,o,.urlset/master.m3u8?t=sxhDLk0aWegkUVYMxJitOLGpnwRmJXtokKF1mPmF0YU&s=1772484385&e=21600&f=14295&i=0.0&sp=0",
          "headers": {
            "Referer": "https://speedostream1.com/"
          }
        },
        {
          "id": "Seasons Greetings (2020) ZEE5 Originals Web Series",
          "title": "Seasons Greetings (2020) ZEE5 Originals Web Series",
          "poster": "https://m.media-amazon.com/images/M/MV5BM2RjYzk1NGEtMjNkZC00ZDRiLWE4NDctNmYzZGFiNTJhMGJhXkEyXkFqcGdeQXVyOTM2ODkzMDk@._V1_FMjpg_UY679_.jpg",
          "stream_url": "https://jnaove.ydc1wes.me/hls2/02/00000/qcil2x6w73mz_,l,o,.urlset/master.m3u8?t=DUASEpsQY2WV-kzqoEwKOc7Zb3uSBhVOVCi-qtq3T-k&s=1772484386&e=21600&f=14271&i=0.0&sp=0",
          "headers": {
            "Referer": "https://speedostream1.com/"
          }
        },
        {
          "id": "Comedy Couple (2020) ZEE5 Originals Web Series",
          "title": "Comedy Couple (2020) ZEE5 Originals Web Series",
          "poster": "https://m.media-amazon.com/images/M/MV5BNzFlMzE3ZjktZTgxMC00MzJhLTlhZDgtMGRhZGMzZTdlOGQ0XkEyXkFqcGdeQXVyMTIxMjE2NzIz._V1_FMjpg_UX1080_.jpg",
          "stream_url": "https://jnaove.ydc1wes.me/hls2/02/00000/glcfz0dgqwjq_,l,o,.urlset/master.m3u8?t=ewitT3PatwVSXWDW45_ba_n2KAzZZ-mv8E4eYNvmHck&s=1772484387&e=21600&f=15594&i=0.0&sp=0",
          "headers": {
            "Referer": "https://speedostream1.com/"
          }
        },
        {
          "id": "Poison (2020) Season 2 Zee5 Originals Web Series",
          "title": "Poison (2020) Season 2 Zee5 Originals Web Series",
          "poster": "https://m.media-amazon.com/images/M/MV5BMDhhM2Q5N2QtOTlkMi00YzQxLTkyODktNjBmMzZmNWU3ZjVhXkEyXkFqcGdeQXVyMTIzMzg0MTM2._V1_SY1000_CR0,0,562,1000_AL_.jpg",
          "stream_url": "https://fringe.ydc1wes.me/hls2/01/00000/5jk6vpb27esc_,l,o,.urlset/master.m3u8?t=FET8UhA437U3IHhYWi-pUWzVw5Jaq3qH2oOExSvUGZk&s=1772484388&e=21600&f=14259&i=0.0&sp=0",
          "headers": {
            "Referer": "https://speedostream1.com/"
          }
        },
        {
          "id": "Abhay (2020) Season 2 Zee5",
          "title": "Abhay (2020) Season 2 Zee5",
          "poster": "https://m.media-amazon.com/images/M/MV5BYjc4ZTk4MWEtMmZlZi00MzQ4LWI2NGYtNzIyNGEyOTQ1ZWQyXkEyXkFqcGdeQXVyMTIyNjk5MTE3._V1_QL50_.jpg",
          "stream_url": "https://aamir.ydc1wes.me/hls2/01/00000/rt7cbbbx4i1a_,l,o,.urlset/master.m3u8?t=nwFAmp8Djdk2jegLBCx2Zbl96hNZWyjlkP-F0xPxxew&s=1772484390&e=21600&f=15585&i=0.0&sp=0",
          "headers": {
            "Referer": "https://speedostream1.com/"
          }
        },
        {
          "id": "Expiry Date (2020) Season 1 Zee5",
          "title": "Expiry Date (2020) Season 1 Zee5",
          "poster": "https://m.media-amazon.com/images/M/MV5BZDA2MjViOTAtZjI4Yy00OTllLTg5MzctMGE5MmQ1NjZjNDE1XkEyXkFqcGdeQXVyMTIzNzk0MzM0._V1_QL50_.jpg",
          "stream_url": "https://harduesx.ydc1wes.me/hls2/01/00000/jtl8m69blmbk_,l,o,.urlset/master.m3u8?t=c2MRL0_VpaIiFu0VOtaS1TZh_rL4g3auR1ivOidV5iM&s=1772484391&e=21600&f=15592&i=0.0&sp=0",
          "headers": {
            "Referer": "https://speedostream1.com/"
          }
        },
        {
          "id": "Forbidden Love: Rules Of The Game (2020) Zee5",
          "title": "Forbidden Love: Rules Of The Game (2020) Zee5",
          "poster": "https://www.themoviedb.org/t/p/w600_and_h900_bestv2/5wnQZtEDC6ea4OLCHmD8OIneWgh.jpg",
          "stream_url": "https://fringe.ydc1wes.me/hls2/01/00000/daksrbux0ug4_,l,o,.urlset/master.m3u8?t=HQzorPbQVMedQkUCF_edDeRNzX56ShSu-AxuK1MY-XE&s=1772484391&e=21600&f=14253&i=0.0&sp=0",
          "headers": {
            "Referer": "https://speedostream1.com/"
          }
        },
        {
          "id": "Forbidden Love: Diagnosis Of Love (2020) Zee5",
          "title": "Forbidden Love: Diagnosis Of Love (2020) Zee5",
          "poster": "https://www.themoviedb.org/t/p/w600_and_h900_bestv2/5wnQZtEDC6ea4OLCHmD8OIneWgh.jpg",
          "stream_url": "https://fringe.ydc1wes.me/hls2/01/00000/ax6v3js3qjhw_,l,o,.urlset/master.m3u8?t=OLF_9gGrEutXK7TScj73B_M7QEedA60Y15EkdCt2GZE&s=1772484392&e=21600&f=14252&i=0.0&sp=0",
          "headers": {
            "Referer": "https://speedostream1.com/"
          }
        },
        {
          "id": "London Confidential (2020)",
          "title": "London Confidential (2020)",
          "poster": "https://m.media-amazon.com/images/M/MV5BYTM3NmQ5MDAtYWNiZS00NDllLWI4NjQtNjc3MDIzM2Q2NWQyXkEyXkFqcGdeQXVyMTE3MDIzODIw._V1_QL50_SY1000_SX1000_AL_.jpg",
          "stream_url": "https://harduesx.ydc1wes.me/hls2/01/00000/t63xnjvgk06s_,l,h,.urlset/master.m3u8?t=zLj9Xd9h9ceKDkHYoJ91AZdnHJOToTPLtIDqBUMptF8&s=1772484393&e=21600&f=14264&i=0.0&sp=0",
          "headers": {
            "Referer": "https://speedostream1.com/"
          }
        },
        {
          "id": "Tiki Taka (2020) ZEE5 Web Series",
          "title": "Tiki Taka (2020) ZEE5 Web Series",
          "poster": "https://in.bmscdn.com/iedb/movies/images/mobile/thumbnail/large/tiki-taka-et00138177-09-09-2020-06-35-58.jpg",
          "stream_url": "https://harduesx.ydc1wes.me/hls2/01/00000/d4cydr140wsj_,l,o,.urlset/master.m3u8?t=hopYW1_VMn8LDBjuj7JGqF5SzpVOTVj_IDqaylNtV-c&s=1772484394&e=21600&f=14289&i=0.0&sp=0",
          "headers": {
            "Referer": "https://speedostream1.com/"
          }
        },
        {
          "id": "Forbidden Love: Arranged Marriage (2020) Zee5",
          "title": "Forbidden Love: Arranged Marriage (2020) Zee5",
          "poster": "https://www.themoviedb.org/t/p/w600_and_h900_bestv2/5wnQZtEDC6ea4OLCHmD8OIneWgh.jpg",
          "stream_url": "https://gustavo.ydc1wes.me/hls2/01/00000/pnqmzjib2n75_,n,h,.urlset/master.m3u8?t=hsazvmwqYqwdq5mfUHiQyxK8n8ZX7iqqB-YJjeWaHfg&s=1772484395&e=21600&f=14251&i=0.0&sp=0",
          "headers": {
            "Referer": "https://speedostream1.com/"
          }
        },
        {
          "id": "Forbidden Love: Anamika (2020) Zee5",
          "title": "Forbidden Love: Anamika (2020) Zee5",
          "poster": "https://www.themoviedb.org/t/p/w600_and_h900_bestv2/5wnQZtEDC6ea4OLCHmD8OIneWgh.jpg",
          "stream_url": "https://aamir.ydc1wes.me/hls2/01/00000/jakm9tdynnzh_,n,h,.urlset/master.m3u8?t=WgpZ1nl5lo88WWSpVDzVzr0P_0ixrqxQsl3-xwKtvFE&s=1772484396&e=21600&f=14250&i=0.0&sp=0",
          "headers": {
            "Referer": "https://speedostream1.com/"
          }
        },
        {
          "id": "Bhanwar (2020) Season 1 Zee5",
          "title": "Bhanwar (2020) Season 1 Zee5",
          "poster": "https://m.media-amazon.com/images/M/MV5BZTUwMTU3YzQtNzY4NS00ZWVjLWI0MmQtNzA4NTQ2MTNkOWY5XkEyXkFqcGdeQXVyMTIyMjIwMDAw._V1_FMjpg_UY480_.jpg",
          "stream_url": "https://jnaove.ydc1wes.me/hls2/02/00000/ng3yv6cfis64_,l,o,.urlset/master.m3u8?t=PjaNlfd93ocfs-5gbcbfKHftBqklGZmuvPGiTWUHxvo&s=1772484397&e=21600&f=15603&i=0.0&sp=0",
          "headers": {
            "Referer": "https://speedostream1.com/"
          }
        },
        {
          "id": "Kaafir (2019) Season 1 Zee5",
          "title": "Kaafir (2019) Season 1 Zee5",
          "poster": "https://m.media-amazon.com/images/M/MV5BMjNjOTZmZjMtNDcxZS00ZTY0LWI3OTQtMDNiODMyYjUxMjM4XkEyXkFqcGdeQXVyNDAzNDk0MTQ@._V1_QL50_SY1000_CR0,0,562,1000_AL_.jpg",
          "stream_url": "https://jnaove.ydc1wes.me/hls2/02/00000/1txvp7z8565l_,l,o,.urlset/master.m3u8?t=k8zmywTaUwLatL1xGkFUOqz4ZGgODvGpmHrZI2G2gmk&s=1772484398&e=21600&f=14236&i=0.0&sp=0",
          "headers": {
            "Referer": "https://speedostream1.com/"
          }
        },
        {
          "id": "Churails (2020) Season 1 Zee5 Web series",
          "title": "Churails (2020) Season 1 Zee5 Web series",
          "poster": "https://m.media-amazon.com/images/M/MV5BZThiYWI3N2UtNjFlMy00ZjlmLThiOTUtYjE5MzRmN2RlYTY3XkEyXkFqcGdeQXVyNTAzMTc1NjE@._V1_QL50_SY1000_CR0,0,809,1000_AL_.jpg",
          "stream_url": "https://jesse.ydc1wes.me/hls2/02/00001/9huwqxy4rvbl_,l,o,.urlset/master.m3u8?t=fziSTAIhU-_sz_dCEDrPkpoMsF4TJMKCDLTNnwlcHgQ&s=1772484399&e=21600&f=15595&i=0.0&sp=0",
          "headers": {
            "Referer": "https://speedostream1.com/"
          }
        },
        {
          "id": "SkyFire (2020) Season 1 Zee5",
          "title": "SkyFire (2020) Season 1 Zee5",
          "poster": "https://m.media-amazon.com/images/M/MV5BMGYxNjdkNjItZDMyMi00Y2UwLWFlYmUtZmFkYmIyNjUwMDlkXkEyXkFqcGdeQXVyOTc0OTQ0OTY@._V1_SY1000_SX1000_AL_.jpg",
          "stream_url": "https://jnaove.ydc1wes.me/hls2/02/00000/gbvcb262diyu_,l,o,.urlset/master.m3u8?t=uEwe14A04D1RMR2cBiIZFVyOfr28LcemD4sukPZL8Gc&s=1772484400&e=21600&f=14272&i=0.0&sp=0",
          "headers": {
            "Referer": "https://speedostream1.com/"
          }
        },
        {
          "id": "Partners for Justice (2020) Season 1 Hindi Dubbed",
          "title": "Partners for Justice (2020) Season 1 Hindi Dubbed",
          "poster": "https://m.media-amazon.com/images/M/MV5BYzEzZGQyNGUtMDhlMS00MmQ1LTlkMGItMzc3MzNjODQxMTUyXkEyXkFqcGdeQXVyNjc3MjQzNTI@._V1_SY1000_CR0,0,668,1000_AL_.jpg",
          "stream_url": "https://dawn.ydc1wes.me/hls2/02/00008/u8qw8yt9qoub_l/master.m3u8?t=SYHZ0JhBrfamPLyFXM3_s5Dx7Ljs8_fjlIOVckYpzS4&s=1772484400&e=21600&f=44194&i=0.0&sp=0",
          "headers": {
            "Referer": "https://speedostream1.com/"
          }
        },
        {
          "id": "Mafia (2020) Season 1 Zee5",
          "title": "Mafia (2020) Season 1 Zee5",
          "poster": "https://m.media-amazon.com/images/M/MV5BNTA1MzA2MWQtMTFkYi00ZDFjLTgwNDgtNDU4ZmM4OTlkZGUwXkEyXkFqcGdeQXVyMTIwNzMxNTU2._V1_QL50_.jpg",
          "stream_url": "https://jnaove.ydc1wes.me/hls2/02/00000/12o5ejgrc735_,l,o,.urlset/master.m3u8?t=DKYefCvkWXpF5ekIh4Tnx3vbGqpZnV8Zj57SQqoCmKU&s=1772484401&e=21600&f=14266&i=0.0&sp=0",
          "headers": {
            "Referer": "https://speedostream1.com/"
          }
        },
        {
          "id": "Kaale Dhande (2019) Season 1 Zee5",
          "title": "Kaale Dhande (2019) Season 1 Zee5",
          "poster": "https://m.media-amazon.com/images/M/MV5BNjBmZjUyYjctNmYyMy00NDcyLTliZjktMDk1ZDA3N2VjZTZjXkEyXkFqcGdeQXVyMTA0MTIzODI4._V1_QL50_.jpg",
          "stream_url": "https://aamir.ydc1wes.me/hls2/01/00000/a0udfem69juh_,l,o,.urlset/master.m3u8?t=7mHLEqF0-gmVlQIn4IXI7Gwlv9kB9Pd3xBxA7e2qPww&s=1772484402&e=21600&f=14239&i=0.0&sp=0",
          "headers": {
            "Referer": "https://speedostream1.com/"
          }
        },
        {
          "id": "Unlock: The Haunted App (2020) Zee5",
          "title": "Unlock: The Haunted App (2020) Zee5",
          "poster": "https://m.media-amazon.com/images/M/MV5BZmYyNGQ1ZjAtNDRlOS00MzUwLTkzZTMtYWU4ZWNkMWUyZmM2XkEyXkFqcGdeQXVyMTE5MjE5NzMw._V1_QL50_SY1000_SX1000_AL_.jpg",
          "stream_url": "https://jnaove.ydc1wes.me/hls2/02/00000/3rwk6zzrbtnl_,l,o,.urlset/master.m3u8?t=696uGiAKGXGUmPg9S9FaDbmzF_tyKes6_gEcAQ_ug4c&s=1772484403&e=21600&f=14290&i=0.0&sp=0",
          "headers": {
            "Referer": "https://speedostream1.com/"
          }
        },
        {
          "id": "Lalbazaar (2020) Season 1 Zee5",
          "title": "Lalbazaar (2020) Season 1 Zee5",
          "poster": "https://m.media-amazon.com/images/M/MV5BMTNmZDA0ZDItZWNkOC00MDFkLWE2YjctNmE5MGZhZDg5ZTk4XkEyXkFqcGdeQXVyMTE2MTc3MzU1._V1_FMjpg_UX480_.jpg",
          "stream_url": "https://aamir.ydc1wes.me/hls2/01/00000/ug3yhzp4socf_,l,o,.urlset/master.m3u8?t=nhEQYpwp4NGAEMqV9bnAym3_xHcNZeyvu0MfKdMp9Ks&s=1772484403&e=21600&f=14261&i=0.0&sp=0",
          "headers": {
            "Referer": "https://speedostream1.com/"
          }
        },
        {
          "id": "Never Kiss Your Best Friend (Lockdown Special) (2020) Season 1",
          "title": "Never Kiss Your Best Friend (Lockdown Special) (2020) Season 1",
          "poster": "https://m.media-amazon.com/images/M/MV5BNjBiYWYxMWItYTNiMy00OTA5LTlhZGQtZTc2NTVkYmY2MTFmXkEyXkFqcGdeQXVyMTE5MjE5NzMw._V1_QL50_.jpg",
          "stream_url": "https://harduesx.ydc1wes.me/hls2/01/00000/q8l7nzlgy146_,l,o,.urlset/master.m3u8?t=uLcvYymKuuTPhD_4CDzv5X8vBKGTaLYkhPAVDMvKEbM&s=1772484405&e=21600&f=14260&i=0.0&sp=0",
          "headers": {
            "Referer": "https://speedostream1.com/"
          }
        },
        {
          "id": "The Casino (2020) Season 1 Zee5",
          "title": "The Casino (2020) Season 1 Zee5",
          "poster": "https://akamaividz2.zee5.com/image/upload/w_630,h_945,c_scale,f_auto,q_auto/resources/0-6-2556/portrait/1920x770_818792301.jpg",
          "stream_url": "https://jnaove.ydc1wes.me/hls2/02/00000/pkigz92mwgpj_,l,o,.urlset/master.m3u8?t=KIZ98yeN-D1y5hZsHuEPEprEtitZS6RdUHVYyEG53TM&s=1772484406&e=21600&f=14294&i=0.0&sp=0",
          "headers": {
            "Referer": "https://speedostream1.com/"
          }
        },
        {
          "id": "Bhalla Calling Bhalla (2020) Season 1 Zee5",
          "title": "Bhalla Calling Bhalla (2020) Season 1 Zee5",
          "poster": "https://m.media-amazon.com/images/M/MV5BOTAzNWQyZmYtM2QyOC00ODYxLTk3NWMtZGZjZDI4MTFiM2ViXkEyXkFqcGdeQXVyMTE2MTc3MzU1._V1_UY1200_CR746,0,630,1200_AL_.jpg",
          "stream_url": "https://harduesx.ydc1wes.me/hls2/01/00001/yagtp13hugfm_,l,o,.urlset/master.m3u8?t=PHKvHTPL8IBiH02iMyPCwZgEyWZuJUlTAVd9I2M8fVU&s=1772484406&e=21600&f=15605&i=0.0&sp=0",
          "headers": {
            "Referer": "https://speedostream1.com/"
          }
        },
        {
          "id": "Kaali (2020) Season 2 Zee5",
          "title": "Kaali (2020) Season 2 Zee5",
          "poster": "https://m.media-amazon.com/images/M/MV5BMjkzYmY3ZDMtZDViYi00NDFjLWE5NDQtYWUxODIwM2Q1NDY4XkEyXkFqcGdeQXVyODM3OTg2MzQ@._V1_FMjpg_UY694_.jpg",
          "stream_url": "https://jnaove.ydc1wes.me/hls2/02/00000/542t4rhfv5im_,l,o,.urlset/master.m3u8?t=c1HvaU3BxDSMpJOYdkNfm2HEfH8KgdQEMolUmLppRVA&s=1772484407&e=21600&f=2592&i=0.0&sp=0",
          "headers": {
            "Referer": "https://speedostream1.com/"
          }
        },
        {
          "id": "Ghoomketu (2020)",
          "title": "Ghoomketu (2020)",
          "poster": "https://m.media-amazon.com/images/M/MV5BOWYwOThhMTQtZTRkYS00MDg0LTg3YTItYjg5MTU1YTU3NjgxXkEyXkFqcGdeQXVyMzQ5Njc3NzU@._V1_QL50_.jpg",
          "stream_url": "https://harduesx.ydc1wes.me/hls2/01/00006/dmoliahhg9lz_,l,h,.urlset/master.m3u8?t=_wTyd7ecVr7M0y1TJagRhW6hDQgbk7d8MZQz13As6PM&s=1772484408&e=21600&f=30799&i=0.0&sp=0",
          "headers": {
            "Referer": "https://speedostream1.com/"
          }
        },
        {
          "id": "Court Martial (2020)",
          "title": "Court Martial (2020)",
          "poster": "https://m.media-amazon.com/images/M/MV5BMDM3MTA5NjAtMDM1Zi00NmU5LWE5NWQtMmVkNTY0ZmRiYWZjXkEyXkFqcGdeQXVyODYxMTEzMzI@._V1_FMjpg_UX886_.jpg",
          "stream_url": "https://harduesx.ydc1wes.me/hls2/01/00000/4mnws84dteoh_,l,o,.urlset/master.m3u8?t=dmMafOetI9nzh2TukVGgLk3jJ9_wgB9S2HdPBy8fCHA&s=1772484408&e=21600&f=15589&i=0.0&sp=0",
          "headers": {
            "Referer": "https://speedostream1.com/"
          }
        },
        {
          "id": "Bombers (2019) Season 1 Zee5",
          "title": "Bombers (2019) Season 1 Zee5",
          "poster": "https://m.media-amazon.com/images/M/MV5BNzZlZWNmMDEtNDBmZi00NmJjLWFmMjMtZDJjNTI1OWQ1Y2JlXkEyXkFqcGdeQXVyODE5NzE3OTE@._V1_QL50_SY1000_CR0,0,692,1000_AL_.jpg",
          "stream_url": "https://jnaove.ydc1wes.me/hls2/02/00000/9d56sd741zdv_,l,o,.urlset/master.m3u8?t=jOJcl6HxJmqBZm-_IxjaGBonEROI_Yl1go39q7iVPKk&s=1772484409&e=21600&f=15598&i=0.0&sp=0",
          "headers": {
            "Referer": "https://speedostream1.com/"
          }
        },
        {
          "id": "The Final Call (2019) Season 1 Zee5 Originals",
          "title": "The Final Call (2019) Season 1 Zee5 Originals",
          "poster": "https://m.media-amazon.com/images/M/MV5BNjcyYjNkOGYtOGU2NC00M2NhLTk4N2QtYWU0MzNjM2U4N2VmXkEyXkFqcGdeQXVyODE5NzE3OTE@._V1_QL50_SY1000_CR0,0,702,1000_AL_.jpg",
          "stream_url": "https://jnaove.ydc1wes.me/hls2/02/00000/psij39sn5dme_,l,o,.urlset/master.m3u8?t=ECkbCTYJ6tKyZa9zmm8QfnINxJcwT8bpbjXYEodEH2U&s=1772484410&e=21600&f=14293&i=0.0&sp=0",
          "headers": {
            "Referer": "https://speedostream1.com/"
          }
        },
        {
          "id": "Auto Shankar (2019) Season 1 Hindi Zee5 Originals",
          "title": "Auto Shankar (2019) Season 1 Hindi Zee5 Originals",
          "poster": "https://m.media-amazon.com/images/M/MV5BNWNmZmY2ZTctOTMzNy00NGUzLTgzNzUtNmFmZjZhNmEzZDM1XkEyXkFqcGdeQXVyODE5NzE3OTE@._V1_FMjpg_UX1000_.jpg",
          "stream_url": "https://aamir.ydc1wes.me/hls2/01/00000/oschpvhkhm4l_,l,o,.urlset/master.m3u8?t=JKCPIgpmEOgZU7IOJZT1y-ncg2dV_EABjKX8apMMjuo&s=1772484411&e=21600&f=15608&i=0.0&sp=0",
          "headers": {
            "Referer": "https://speedostream1.com/"
          }
        },
        {
          "id": "Ateet (2020) Zee5 Originals",
          "title": "Ateet (2020) Zee5 Originals",
          "poster": "https://m.media-amazon.com/images/M/MV5BOTlkYmYxODEtMzQ0NS00NjM5LTg1NDQtYWVhOTJjOWU0NGY0XkEyXkFqcGdeQXVyODI1Nzg1OTQ@._V1_FMjpg_UX601_.jpg",
          "stream_url": "https://jnaove.ydc1wes.me/hls2/02/00000/l9o3mgpgyit0_,l,o,.urlset/master.m3u8?t=PMZHxJwGlKXt3vPPqmABlom5_wi1skHc2AA8IN5FpTY&s=1772484412&e=21600&f=15612&i=0.0&sp=0",
          "headers": {
            "Referer": "https://speedostream1.com/"
          }
        },
        {
          "id": "Purush (2020) Zee5 Originals",
          "title": "Purush (2020) Zee5 Originals",
          "poster": "https://m.media-amazon.com/images/M/MV5BNGJmZTY3OGUtYWRhOS00YzMyLWIzMjEtZDM1ZmU4NzQ5ODAyXkEyXkFqcGdeQXVyMzQ5MzkwMDY@._V1_FMjpg_UX781_.jpg",
          "stream_url": "https://harduesx.ydc1wes.me/hls2/01/00001/t6qrkfhq7krp_,l,o,.urlset/master.m3u8?t=9TfN6dty1ecH0gb0OgQ6nlcZNRgh4uq_7R3YSLwqTZs&s=1772484413&e=21600&f=14262&i=0.0&sp=0",
          "headers": {
            "Referer": "https://speedostream1.com/"
          }
        },
        {
          "id": "Mushk (2020) ZEE5 Originals",
          "title": "Mushk (2020) ZEE5 Originals",
          "poster": "https://m.media-amazon.com/images/M/MV5BOGM1MjhmYzgtMjk4YS00MTc0LThlNzMtNzAzYTRlYjhlZDgxXkEyXkFqcGdeQXVyMTEwMjI4NzYy._V1_FMjpg_UY689_.jpg",
          "stream_url": "https://jnaove.ydc1wes.me/hls2/02/00000/en6w6p3iai6s_,l,o,.urlset/master.m3u8?t=vOQMr8YWbVHtAFhgP6wImeXrIGv4VfYegwaImSLcRhU&s=1772484414&e=21600&f=2676&i=0.0&sp=0",
          "headers": {
            "Referer": "https://speedostream1.com/"
          }
        },
        {
          "id": "One Stop For Love (2020) Zee5 Originals",
          "title": "One Stop For Love (2020) Zee5 Originals",
          "poster": "https://m.media-amazon.com/images/M/MV5BZmFkZDVlMDEtNGY4Yy00Y2YyLTg4NGYtOTQ5MTVhZTcyNTQxXkEyXkFqcGdeQXVyNTM3MzMxNTU@._V1_UY268_CR147,0,182,268_AL_.jpg",
          "stream_url": "https://harduesx.ydc1wes.me/hls2/01/00001/1d8jznbkb8ja_,l,o,.urlset/master.m3u8?t=x0U941C1AmsoX0RSIOoZQASn5p_B0YEfvTAX_gvWjG0&s=1772484415&e=21600&f=14265&i=0.0&sp=0",
          "headers": {
            "Referer": "https://speedostream1.com/"
          }
        },
        {
          "id": "Water Bottle (2019) Zee5",
          "title": "Water Bottle (2019) Zee5",
          "poster": "https://bingeddata.s3.amazonaws.com/uploads/2020/11/aztLseHbOiQZOXV4rRMVaDqTZs2.jpg",
          "stream_url": "https://harduesx.ydc1wes.me/hls2/01/00000/ii304krlzbcq_,l,o,.urlset/master.m3u8?t=gPXck6tL335XtghXDLkAYvTqI0_SvRxaHie24QX8GM0&s=1772484416&e=21600&f=14291&i=0.0&sp=0",
          "headers": {
            "Referer": "https://speedostream1.com/"
          }
        },
        {
          "id": "The Lovely Mrs. Mookherjee (2019) Zee5 Originals",
          "title": "The Lovely Mrs. Mookherjee (2019) Zee5 Originals",
          "poster": "https://m.media-amazon.com/images/M/MV5BYmEzNmJiYjYtN2FiMC00YjdjLWE5MmEtZWVjZGExM2RiNDc0XkEyXkFqcGdeQXVyMTI0NTk3OTMy._V1_FMjpg_UY651_.jpg",
          "stream_url": "https://jnaove.ydc1wes.me/hls2/02/00000/ko1v4x4ml3t3_,l,o,.urlset/master.m3u8?t=4H23c5M_0g2JOTGymXbkskdlSqioC3AQpqIIYW7iETA&s=1772484416&e=21600&f=14275&i=0.0&sp=0",
          "headers": {
            "Referer": "https://speedostream1.com/"
          }
        },
        {
          "id": "Hutatma (2019) Season 2 Zee5",
          "title": "Hutatma (2019) Season 2 Zee5",
          "poster": "https://m.media-amazon.com/images/M/MV5BMGMzNGU0MmMtODgxZi00MmJjLTlmZGQtY2IyY2E1NmRiZGNkXkEyXkFqcGdeQXVyODE5NzE3OTE@._V1_FMjpg_UX1000_.jpg",
          "stream_url": "https://harduesx.ydc1wes.me/hls2/01/00000/9vfvrblcvjp1_,l,o,.urlset/master.m3u8?t=_PrwvobZPCj1KQfuIqywmoxzcFJT9rbR5iwfcPVkllI&s=1772484417&e=21600&f=14247&i=0.0&sp=0",
          "headers": {
            "Referer": "https://speedostream1.com/"
          }
        },
        {
          "id": "Ishq Aaj Kal (2019) Season 1 Zee5",
          "title": "Ishq Aaj Kal (2019) Season 1 Zee5",
          "poster": "https://www.themoviedb.org/t/p/w600_and_h900_bestv2/rP5v24WDAyXKC42V0gJuI1bE8tE.jpg",
          "stream_url": "https://jnaove.ydc1wes.me/hls2/02/00000/k1rdudp9egqj_,l,o,.urlset/master.m3u8?t=aEXfFWdlZ7DODk8pn-loEmRfEUyJbQQxwvDIj83FRFk&s=1772484418&e=21600&f=14244&i=0.0&sp=0",
          "headers": {
            "Referer": "https://speedostream1.com/"
          }
        },
        {
          "id": "Ishq Aaj Kal (2019) Season 4 Zee5",
          "title": "Ishq Aaj Kal (2019) Season 4 Zee5",
          "poster": "https://m.media-amazon.com/images/M/MV5BYWEzODQ2ODYtZWMzNy00OTA1LTg2MWUtMmJjOWM0ZDk0OTc1XkEyXkFqcGdeQXVyNjA4NTk0NjU@._V1_UY268_CR147,0,182,268_AL_.jpg",
          "stream_url": "https://jnaove.ydc1wes.me/hls2/02/00000/ugf6fa0skw52_,l,o,.urlset/master.m3u8?t=_dn16oPBrEn_X7AzBKl0JEz3as7YTTh-3f4frLK6PHo&s=1772484419&e=21600&f=14241&i=0.0&sp=0",
          "headers": {
            "Referer": "https://speedostream1.com/"
          }
        },
        {
          "id": "Abhay (2019) Season 1 Zee5",
          "title": "Abhay (2019) Season 1 Zee5",
          "poster": "https://m.media-amazon.com/images/M/MV5BMzZlMzYwOGEtMWQ0ZC00MTQ0LTk1YzUtODhmM2M2NDM4YjI0XkEyXkFqcGdeQXVyMjMwMDY0NjY@._V1_QL50_SY1000_CR0,0,728,1000_AL_.jpg",
          "stream_url": "https://aamir.ydc1wes.me/hls2/01/00001/tw684eis3ck2_,l,o,.urlset/master.m3u8?t=tPtMjhN_xtVxCTs1Uo4MvJWOrAZ5CJxmrWcET7IP2fQ&s=1772484419&e=21600&f=15613&i=0.0&sp=0",
          "headers": {
            "Referer": "https://speedostream1.com/"
          }
        },
        {
          "id": "Kannamoochi (2020) Season 1 Hindi Dubbed",
          "title": "Kannamoochi (2020) Season 1 Hindi Dubbed",
          "poster": "https://akamaividz2.zee5.com/image/upload/w_630,h_945,c_scale,f_webp,q_auto:eco/resources/0-6-2530/portrait/1920x770_476691420.jpg",
          "stream_url": "https://harduesx.ydc1wes.me/hls2/01/00001/olnlv4wkixka_,l,o,.urlset/master.m3u8?t=ivGrAKgzGYTWP660_Xd9eUgMUbd_szjGPh9jz5P4_8A&s=1772484420&e=21600&f=14237&i=0.0&sp=0",
          "headers": {
            "Referer": "https://speedostream1.com/"
          }
        },
        {
          "id": "State of Siege 26/11 (2020) Season 1 Zee5",
          "title": "State of Siege 26/11 (2020) Season 1 Zee5",
          "poster": "https://m.media-amazon.com/images/M/MV5BN2EzMGNmMWQtYzBmZi00NWM2LWI2YzItMGQ3NjdlNTg5NjNmXkEyXkFqcGdeQXVyMTA5NDI0NDQz._V1_FMjpg_UX1080_.jpg",
          "stream_url": "https://aamir.ydc1wes.me/hls2/01/00001/4l4thvby66au_,l,o,.urlset/master.m3u8?t=Pg51-uO0WNcW-_r-yp3xRlcH1tor1WfEtn4Fgq-_-KU&s=1772484421&e=21600&f=14257&i=0.0&sp=0",
          "headers": {
            "Referer": "https://speedostream1.com/"
          }
        },
        {
          "id": "Kaali (2018) Season 1 Zee5",
          "title": "Kaali (2018) Season 1 Zee5",
          "poster": "https://m.media-amazon.com/images/M/MV5BMjkzYmY3ZDMtZDViYi00NDFjLWE5NDQtYWUxODIwM2Q1NDY4XkEyXkFqcGdeQXVyODM3OTg2MzQ@._V1_QL50_SY1000_CR0,0,690,1000_AL_.jpg",
          "stream_url": "https://harduesx.ydc1wes.me/hls2/01/00001/q089ldtginrs_,l,o,.urlset/master.m3u8?t=IIR1Ov1GHcP8Ye2xtYvovjQIqiQ6QewtZcEOgucXqF8&s=1772484422&e=21600&f=14238&i=0.0&sp=0",
          "headers": {
            "Referer": "https://speedostream1.com/"
          }
        },
        {
          "id": "Body Massage (2019)",
          "title": "Body Massage (2019)",
          "poster": "https://m.media-amazon.com/images/M/MV5BZDZmNTc5NWUtMGMxMC00ZDc3LTgxYzEtZjdhODIzZmIyNTQ1XkEyXkFqcGdeQXVyMjkyOTAwMzk@._V1_FMjpg_UX720_.jpg",
          "stream_url": "https://harduesx.ydc1wes.me/hls2/01/00004/cp8iks93yvp3_,l,h,.urlset/master.m3u8?t=-nPy_zcloF87Ll7CoorVPNa9-p86H04kkug8caxb48A&s=1772484423&e=21600&f=21656&i=0.0&sp=0",
          "headers": {
            "Referer": "https://speedostream1.com/"
          }
        },
        {
          "id": "Chadarangam (2020) Season 1 Hindi Dubbed (Zee5)",
          "title": "Chadarangam (2020) Season 1 Hindi Dubbed (Zee5)",
          "poster": "https://www.themoviedb.org/t/p/w600_and_h900_bestv2/uXxF8fvVvcZINgwN4oIqAwaqr51.jpg",
          "stream_url": "https://harduesx.ydc1wes.me/hls2/01/00001/9bxn11anwwr6_,l,o,.urlset/master.m3u8?t=CmOj8XYVW6b57Ojjnuwn3gqj4Hr6OR5E7BmymKjUKcw&s=1772484423&e=21600&f=15599&i=0.0&sp=0",
          "headers": {
            "Referer": "https://speedostream1.com/"
          }
        },
        {
          "id": "RejctX (2019) Season 1 Complete",
          "title": "RejctX (2019) Season 1 Complete",
          "poster": "https://m.media-amazon.com/images/M/MV5BNGM4OGE1NzAtMjIzOS00ZDY1LWFhNzYtMzFhZWM5OGI1ZGE3XkEyXkFqcGdeQXVyMTA4NTc3NTQx._V1_FMjpg_UX1080_.jpg",
          "stream_url": "https://jnaove.ydc1wes.me/hls2/02/00000/nisnaacgxs9k_,l,o,.urlset/master.m3u8?t=_crsDe9CajecG2T4zAEidOY0vdRMzHe2v4jkRW6NhcI&s=1772484424&e=21600&f=2612&i=0.0&sp=0",
          "headers": {
            "Referer": "https://speedostream1.com/"
          }
        },
        {
          "id": "Love Bites (2020) Season 2 Zee5",
          "title": "Love Bites (2020) Season 2 Zee5",
          "poster": "https://m.media-amazon.com/images/M/MV5BMmU2NWVjMjktMzJkOC00YjRkLWIyOTgtNjQ5OTMxM2ZkN2M1XkEyXkFqcGdeQXVyODE5NzE3OTE@._V1_QL50_.jpg",
          "stream_url": "https://gustavo.ydc1wes.me/hls2/01/00001/ii9e44g7w08e_,l,o,.urlset/master.m3u8?t=zKRFrKVfil3OSzvIVfQ_pUw9RhbRHC_HCNZdLyqt1VU&s=1772484425&e=21600&f=12136&i=0.0&sp=0",
          "headers": {
            "Referer": "https://speedostream1.com/"
          }
        },
        {
          "id": "Anaganaga Once Upon A Time (2020) Season 1 Hindi Zee5",
          "title": "Anaganaga Once Upon A Time (2020) Season 1 Hindi Zee5",
          "poster": "https://m.media-amazon.com/images/M/MV5BYjhmNzM1NDYtMDYwOC00ZmExLTk3OWYtN2Y0ZmQzMTU2ZDA2XkEyXkFqcGdeQXVyMTEyNzU2MTEx._V1_FMjpg_UX1125_.jpg",
          "stream_url": "https://jnaove.ydc1wes.me/hls2/02/00001/fhkf7cnx2rlz_,l,o,.urlset/master.m3u8?t=_dpuVS0vZZtEAKgIX0j1H_Jt-gXc_6148muCLJjxLl0&s=1772484426&e=21600&f=15611&i=0.0&sp=0",
          "headers": {
            "Referer": "https://speedostream1.com/"
          }
        },
        {
          "id": "Judgement Day (2020) Season 1 Zee5 Web Series",
          "title": "Judgement Day (2020) Season 1 Zee5 Web Series",
          "poster": "https://akamaividz2.zee5.com/image/upload/w_630,h_945,c_scale,f_webp,q_auto:eco/resources/0-6-2362/portrait/1920x770_476968684.jpg",
          "stream_url": "https://harduesx.ydc1wes.me/hls2/01/00001/gsta5j31bvkv_,l,o,.urlset/master.m3u8?t=8qRBX5YXwlKRHCfDsH3siUbQrArYe2P237C9a6M1mDM&s=1772484427&e=21600&f=14240&i=0.0&sp=0",
          "headers": {
            "Referer": "https://speedostream1.com/"
          }
        },
        {
          "id": "Three Half Bottles (2019) Season 1 Zee5",
          "title": "Three Half Bottles (2019) Season 1 Zee5",
          "poster": "https://m.media-amazon.com/images/M/MV5BNTI5MDRlNzMtODBjZC00YmUwLWEwNjYtM2E0MDA2MzUyMjg3XkEyXkFqcGdeQXVyMjM2ODI5MjI@._V1_QL50_SY1000_SX1000_AL_.jpg",
          "stream_url": "https://harduesx.ydc1wes.me/hls2/01/00001/trv9s2ump2jk_,l,o,.urlset/master.m3u8?t=9fL5Tdzpv7-ahT81dugK9tO26DdVo0eLQ9gdPJ92mWM&s=1772484427&e=21600&f=14292&i=0.0&sp=0",
          "headers": {
            "Referer": "https://speedostream1.com/"
          }
        },
        {
          "id": "Hawala (2019) Season 1 Zee5",
          "title": "Hawala (2019) Season 1 Zee5",
          "poster": "https://m.media-amazon.com/images/M/MV5BNjhiODg3ZDYtNDY5Yi00MDI5LWE2NGEtYTAyNDdiZTJhNjkwXkEyXkFqcGdeQXVyMzY0NTM4Nzk@._V1_FMjpg_UY1280_.jpg",
          "stream_url": "https://harduesx.ydc1wes.me/hls2/01/00001/8kl3ffkt3ssf_,l,o,.urlset/master.m3u8?t=rBDoXbkB7obR3f7N6qo5gWV8pnFguiyiy9uAcyifM6Q&s=1772484428&e=21600&f=14246&i=0.0&sp=0",
          "headers": {
            "Referer": "https://speedostream1.com/"
          }
        },
        {
          "id": "Jamai 2.0 (2019) Season 1 Zee5",
          "title": "Jamai 2.0 (2019) Season 1 Zee5",
          "poster": "https://m.media-amazon.com/images/M/MV5BMTk5NjM0ZWItMzIxYy00MDE3LTlhZmQtZTk3Njg5ZDU0ZDg5XkEyXkFqcGdeQXVyODAzNzAwOTU@._V1_QL50_.jpg",
          "stream_url": "https://harduesx.ydc1wes.me/hls2/01/00001/27enojybbtip_,l,o,.urlset/master.m3u8?t=3-0WvBQk6qXPYydTtHaEGAPitV-XZ0a2L7R9h-g4esw&s=1772484429&e=21600&f=14242&i=0.0&sp=0",
          "headers": {
            "Referer": "https://speedostream1.com/"
          }
        },
        {
          "id": "Police Diary 2.0 (2019) Season 1 Zee5",
          "title": "Police Diary 2.0 (2019) Season 1 Zee5",
          "poster": "https://m.media-amazon.com/images/M/MV5BZjJkMmY4N2ItOGE0Zi00MjI2LWIyMjUtOWFiMzU4ZmIzZjMwXkEyXkFqcGdeQXVyOTU2NDQ3NTU@._V1_FMjpg_UX1080_.jpg",
          "stream_url": "https://jnaove.ydc1wes.me/hls2/02/00002/8ru0ehx95nrx_l/master.m3u8?t=e4fDb3wCwJ_LFwhNCw_zImSPQ2R0ht7vXCTroEwtuxQ&s=1772484430&e=21600&f=14268&i=0.0&sp=0",
          "headers": {
            "Referer": "https://speedostream1.com/"
          }
        },
        {
          "id": "Love Sleep Repeat (2019) Season 1 Zee5",
          "title": "Love Sleep Repeat (2019) Season 1 Zee5",
          "poster": "https://m.media-amazon.com/images/M/MV5BMmU2NWVjMjktMzJkOC00YjRkLWIyOTgtNjQ5OTMxM2ZkN2M1XkEyXkFqcGdeQXVyODE5NzE3OTE@._V1_FMjpg_UX523_.jpg",
          "stream_url": "https://oldfils.ydc1wes.me/hls2/01/00001/40r92env8gzv_,l,o,.urlset/master.m3u8?t=210KC1y2Sk_bbY8-_l9r5gu5JHXUgFzieU2PKWijR1g&s=1772484430&e=21600&f=14263&i=0.0&sp=0",
          "headers": {
            "Referer": "https://speedostream1.com/"
          }
        },
        {
          "id": "Bhram (2019) Zee5",
          "title": "Bhram (2019) Zee5",
          "poster": "https://m.media-amazon.com/images/M/MV5BNDI2M2E2YzAtMjgyMS00MDJiLTkxZTktMjg5NjBlNjczODFlXkEyXkFqcGdeQXVyNjkyNjYxNDc@._V1_QL50_.jpg",
          "stream_url": "https://jesse.ydc1wes.me/hls2/02/00001/mt7sl3xxircr_,l,o,.urlset/master.m3u8?t=lF0JUp-Er0wKTLqprJPJ5-RIEJAHvvsb-tfvw7KsbYU&s=1772484431&e=21600&f=15600&i=0.0&sp=0",
          "headers": {
            "Referer": "https://speedostream1.com/"
          }
        },
        {
          "id": "The Lovely Mrs Mookherjee (2019) Hindi Dubbed",
          "title": "The Lovely Mrs Mookherjee (2019) Hindi Dubbed",
          "poster": "https://m.media-amazon.com/images/M/MV5BYmEzNmJiYjYtN2FiMC00YjdjLWE5MmEtZWVjZGExM2RiNDc0XkEyXkFqcGdeQXVyMTI0NTk3OTMy._V1_FMjpg_UY943_.jpg",
          "stream_url": "https://jnaove.ydc1wes.me/hls2/02/00000/ko1v4x4ml3t3_,l,o,.urlset/master.m3u8?t=n9q1ayrFshvDqTrYrvWAPfB3-U8KV5OY4TgNH2Z-nKA&s=1772484432&e=21600&f=14275&i=0.0&sp=0",
          "headers": {
            "Referer": "https://speedostream1.com/"
          }
        },
        {
          "id": "Bhoot Purva (2019) Season 1 ZEE5 Originals Web Series",
          "title": "Bhoot Purva (2019) Season 1 ZEE5 Originals Web Series",
          "poster": "https://m.media-amazon.com/images/M/MV5BMTRkN2EwNjAtYWE3OS00MmUwLTlhN2QtZGM5OTEzMWQ4N2Y2XkEyXkFqcGdeQXVyODE5NzE3OTE@._V1_FMjpg_UX636_.jpg",
          "stream_url": "https://jnaove.ydc1wes.me/hls2/02/00000/oss8t6m7oy3x_,l,o,.urlset/master.m3u8?t=sdjJqQf-rT6KZNgp_lMygWFxeK-iOYUYJgqoiI299m0&s=1772484432&e=21600&f=15604&i=0.0&sp=0",
          "headers": {
            "Referer": "https://speedostream1.com/"
          }
        },
        {
          "id": "Hutatma (2019) Season 1 ZEE5 Originals Web Series",
          "title": "Hutatma (2019) Season 1 ZEE5 Originals Web Series",
          "poster": "https://m.media-amazon.com/images/M/MV5BMGMzNGU0MmMtODgxZi00MmJjLTlmZGQtY2IyY2E1NmRiZGNkXkEyXkFqcGdeQXVyODE5NzE3OTE@._V1_FMjpg_UX1000_.jpg",
          "stream_url": "https://harduesx.ydc1wes.me/hls2/01/00001/4636s5gbfbee_,l,o,.urlset/master.m3u8?t=OnM7q8dW6OfCfEvRY15wK3j5r5j15HCqU_BwYjq-qtk&s=1772484433&e=21600&f=14245&i=0.0&sp=0",
          "headers": {
            "Referer": "https://speedostream1.com/"
          }
        },
        {
          "id": "Ishq Aaj Kal (2019) Season 2 Zee5",
          "title": "Ishq Aaj Kal (2019) Season 2 Zee5",
          "poster": "https://m.media-amazon.com/images/M/MV5BYWEzODQ2ODYtZWMzNy00OTA1LTg2MWUtMmJjOWM0ZDk0OTc1XkEyXkFqcGdeQXVyNjA4NTk0NjU@._V1_UY268_CR147,0,182,268_AL_.jpg",
          "stream_url": "https://harduesx.ydc1wes.me/hls2/01/00001/rf5opu506r1d_,l,o,.urlset/master.m3u8?t=Ug2SvPeNt6CmBznGmgSNGs3y-xtOHMN-icKjuDtUq14&s=1772484433&e=21600&f=14243&i=0.0&sp=0",
          "headers": {
            "Referer": "https://speedostream1.com/"
          }
        }
      ]
    }
  ]
}